{
"quest info: ": {
"name": "$CUREWER",
"questType": "Vampire/Lycanthropy",
"membership": "None",
"reputation": 0,
"delivery": "Unknown",
"childSafe": false,
"questId": 0,
"faction": "None",
"resourceId": 0,
"resourceFileName": "",
"hasDebugInfo": false
}
,"items: [4]": {
" 0: i_letter: Artifact Flammable Parchment [1020]": {
"variable": "i_letter",
"rewardType": "Artifact",
"category": "Flammable",
"itemId": 5,
"textRecordId1": 0,
"textRecordId2": 1020,
"index": 0,
"unknown1": 0
},
" 1: i_00000c7e: Artifact CreatureIngredients1 Werewolfs_blood": {
"variable": "i_00000c7e",
"rewardType": "Artifact",
"category": "CreatureIngredients1",
"itemId": 0,
"textRecordId1": 0,
"textRecordId2": 0,
"index": 1,
"unknown1": 0
},
" 2: i_map: Artifact Flammable Parchment [1060]": {
"variable": "i_map",
"rewardType": "Artifact",
"category": "Flammable",
"itemId": 5,
"textRecordId1": 0,
"textRecordId2": 1060,
"index": 2,
"unknown1": 0
},
" 3: i_00000634: Artifact Flammable Parchment [1061]": {
"variable": "i_00000634",
"rewardType": "Artifact",
"category": "Flammable",
"itemId": 5,
"textRecordId1": 0,
"textRecordId2": 1061,
"index": 3,
"unknown1": 0
}
}
,"npcs: [6]": {
" 0: n_priest: Female ": {
"variable": "n_priest",
"gender": "Female",
"facePictureIndex": 40,
"factionType": 14,
"faction": "None",
"factionRaw": 0,
"textRecordId1": 0,
"textRecordId2": 0,
"index": 0,
"unknown1": 0
},
" 1: n_child: Female Children": {
"variable": "n_child",
"gender": "Female",
"facePictureIndex": 1,
"factionType": 65535,
"faction": "Children",
"factionRaw": 514,
"textRecordId1": 0,
"textRecordId2": 0,
"index": 1,
"unknown1": 0
},
" 2: n_shaman: Female Sheogorath": {
"variable": "n_shaman",
"gender": "Female",
"facePictureIndex": 1,
"factionType": 65534,
"faction": "Sheogorath",
"factionRaw": 9,
"textRecordId1": 1011,
"textRecordId2": 1012,
"index": 2,
"unknown1": 0
},
" 3: n_alchemist: Female ": {
"variable": "n_alchemist",
"gender": "Female",
"facePictureIndex": 0,
"factionType": 0,
"faction": "None",
"factionRaw": 0,
"textRecordId1": 0,
"textRecordId2": 0,
"index": 3,
"unknown1": 0
},
" 4: n_father: Female ": {
"variable": "n_father",
"gender": "Female",
"facePictureIndex": 5,
"factionType": 16,
"faction": "None",
"factionRaw": 0,
"textRecordId1": 1013,
"textRecordId2": 1014,
"index": 4,
"unknown1": 0
},
" 5: n_local: Female ": {
"variable": "n_local",
"gender": "Female",
"facePictureIndex": 0,
"factionType": 17,
"faction": "None",
"factionRaw": 0,
"textRecordId1": 0,
"textRecordId2": 0,
"index": 5,
"unknown1": 0
}
}
,"locations: [4]": {
" 0: l_mapdung: OutOfTown DesecratedTemple": {
"variable": "l_mapdung",
"generalLocation": "OutOfTown",
"locationType": 4,
"LocationType": "DesecratedTemple",
"fineLocation": 1,
"knownLocation": "None",
"doorSelector": 1,
"textRecordId1": 0,
"textRecordId2": 0,
"index": 0,
"flags": 0,
"objPtr": 0,
"unknown1": 13312
},
" 1: l_00000cb8: Specific GlenmorilCoven": {
"variable": "l_00000cb8",
"generalLocation": "Specific",
"locationType": 1,
"LocationType": "SpecificLocation",
"fineLocation": 50008,
"knownLocation": "GlenmorilCoven",
"doorSelector": -1,
"textRecordId1": 0,
"textRecordId2": 0,
"index": 1,
"flags": 0,
"objPtr": 0,
"unknown1": 13312
},
" 2: l_childhouse: OutOfTown House2": {
"variable": "l_childhouse",
"generalLocation": "OutOfTown",
"locationType": 18,
"LocationType": "House2",
"fineLocation": 0,
"knownLocation": "None",
"doorSelector": 0,
"textRecordId1": 0,
"textRecordId2": 0,
"index": 2,
"flags": 0,
"objPtr": 0,
"unknown1": 13312
},
" 3: l_hintdung: OutOfTown RuinedCastle": {
"variable": "l_hintdung",
"generalLocation": "OutOfTown",
"locationType": 11,
"LocationType": "RuinedCastle",
"fineLocation": 1,
"knownLocation": "None",
"doorSelector": 1,
"textRecordId1": 0,
"textRecordId2": 0,
"index": 3,
"flags": 0,
"objPtr": 0,
"unknown1": 13312
}
}
,"timers: [2]": {
" 0: t_00006cc3: Random": {
"variable": "t_00006cc3",
"type": "Random",
"minimum": "7.00:00:00",
"maximum": "27.23:40:00",
"link1": -234881024,
"link2": 12,
"duration": 0,
"started": 0,
"flags": 1,
"index": 0
},
" 1: t_huntstart: TwoLinksPlus": {
"variable": "t_huntstart",
"type": "TwoLinksPlus",
"minimum": "00:00:00",
"maximum": "00:00:00",
"link1": 0,
"link2": 5,
"duration": 0,
"started": 0,
"flags": 769,
"index": 1
}
}
,"mobs: [2]": {
" 0: m_0003808b: 1 Knight": {
"variable": "m_0003808b",
"type": "Knight",
"count": 1,
"null1": 0,
"null2": 0,
"index": 0
},
" 1: m_wereboar: 1 Wereboar": {
"variable": "m_wereboar",
"type": "Wereboar",
"count": 1,
"null1": 0,
"null2": 0,
"index": 1
}
}
,"opCodes: [60]": {
" 0:  >> WhenTimerExpires (t_huntstart): set s_1": {
"opCode": 12,
"argCount": 2,
"arguments:": {
"0: s_9": {
"type": "State",
"value": "9",
"not": "False",
"index": "9",
"unknown1": "100680946"
},
"1: t_huntstart": {
"type": "Timer",
"value": "1",
"not": "False",
"index": "1",
"unknown1": "14"
}
},
"messageId": -1,
"flags": 0,
"lastUpdate": 111
},
" 1: s_1 => CreateLogEntry (1050, 0)": {
"opCode": 23,
"argCount": 3,
"arguments:": {
"0: s_1": {
"type": "State",
"value": "1",
"not": "False",
"index": "1",
"unknown1": "100680946"
},
"1: 1050": {
"type": "Value",
"value": "1050",
"not": "False",
"index": "0",
"unknown1": "14"
},
"2: 0": {
"type": "Value",
"value": "0",
"not": "False",
"index": "0",
"unknown1": "1156761600"
}
},
"messageId": -1,
"flags": 0,
"lastUpdate": 111
},
" 2:  => PlaceItemOnPlayer (i_letter) [Msg 1045]": {
"opCode": 76,
"argCount": 2,
"arguments:": {
"0: _": {
"type": "State",
"value": "-1",
"not": "False",
"index": "255",
"unknown1": "100680946"
},
"1: i_letter": {
"type": "Item",
"value": "0",
"not": "False",
"index": "0",
"unknown1": "14"
}
},
"messageId": 1045,
"flags": 0,
"lastUpdate": 111
},
" 3:  >> WhenItemIsUsed (i_map): set s_10": {
"opCode": 57,
"argCount": 3,
"arguments:": {
"0: _": {
"type": "State",
"value": "-1",
"not": "False",
"index": "255",
"unknown1": "100680946"
},
"1: s_10": {
"type": "State",
"value": "10",
"not": "False",
"index": "10",
"unknown1": "14"
},
"2: i_map": {
"type": "Item",
"value": "2",
"not": "False",
"index": "2",
"unknown1": "1156761600"
}
},
"messageId": -1,
"flags": 0,
"lastUpdate": 111
},
" 4: s_10 => ShowLocationOnMap (l_00000cb8, 60, 81312)": {
"opCode": 27,
"argCount": 4,
"arguments:": {
"0: s_10": {
"type": "State",
"value": "10",
"not": "False",
"index": "10",
"unknown1": "100680946"
},
"1: l_00000cb8": {
"type": "Location",
"value": "1",
"not": "False",
"index": "1",
"unknown1": "14"
},
"2: 60": {
"type": "Value",
"value": "60",
"not": "False",
"index": "0",
"unknown1": "1156761600"
},
"3: 81312": {
"type": "Value",
"value": "81312",
"not": "False",
"index": "0",
"unknown1": "1997668352"
}
},
"messageId": -1,
"flags": 0,
"lastUpdate": 111
},
" 5:  => EnsureNpcLocation (l_childhouse)": {
"opCode": 81,
"argCount": 3,
"arguments:": {
"0: _": {
"type": "State",
"value": "-1",
"not": "False",
"index": "255",
"unknown1": "100680946"
},
"1: l_childhouse": {
"type": "Location",
"value": "2",
"not": "False",
"index": "2",
"unknown1": "14"
},
"2: ": {
"type": "Npc",
"value": "-1",
"not": "False",
"index": "255",
"unknown1": "1156761600"
}
},
"messageId": -1,
"flags": 0,
"lastUpdate": 111
},
" 6:  => RemoveTopics (n_father)": {
"opCode": 11,
"argCount": 4,
"arguments:": {
"0: _": {
"type": "State",
"value": "-1",
"not": "False",
"index": "255",
"unknown1": "100680946"
},
"1: ": {
"type": "Location",
"value": "-1",
"not": "False",
"index": "255",
"unknown1": "14"
},
"2: n_father": {
"type": "Npc",
"value": "4",
"not": "False",
"index": "4",
"unknown1": "1156761600"
},
"3: ": {
"type": "Item",
"value": "-1",
"not": "False",
"index": "255",
"unknown1": "1997668352"
}
},
"messageId": -1,
"flags": 0,
"lastUpdate": 111
},
" 7:  => RemoveTopics (l_childhouse, n_child)": {
"opCode": 11,
"argCount": 4,
"arguments:": {
"0: _": {
"type": "State",
"value": "-1",
"not": "False",
"index": "255",
"unknown1": "100680946"
},
"1: l_childhouse": {
"type": "Location",
"value": "2",
"not": "False",
"index": "2",
"unknown1": "14"
},
"2: n_child": {
"type": "Npc",
"value": "1",
"not": "False",
"index": "1",
"unknown1": "1156761600"
},
"3: ": {
"type": "Item",
"value": "-1",
"not": "False",
"index": "255",
"unknown1": "1997668352"
}
},
"messageId": -1,
"flags": 0,
"lastUpdate": 111
},
" 8:  => RemoveTopics (l_00000cb8, n_shaman)": {
"opCode": 11,
"argCount": 4,
"arguments:": {
"0: _": {
"type": "State",
"value": "-1",
"not": "False",
"index": "255",
"unknown1": "100680946"
},
"1: l_00000cb8": {
"type": "Location",
"value": "1",
"not": "False",
"index": "1",
"unknown1": "14"
},
"2: n_shaman": {
"type": "Npc",
"value": "2",
"not": "False",
"index": "2",
"unknown1": "1156761600"
},
"3: ": {
"type": "Item",
"value": "-1",
"not": "False",
"index": "255",
"unknown1": "1997668352"
}
},
"messageId": -1,
"flags": 0,
"lastUpdate": 111
},
" 9:  => RemoveTopics (l_hintdung, n_alchemist)": {
"opCode": 11,
"argCount": 4,
"arguments:": {
"0: _": {
"type": "State",
"value": "-1",
"not": "False",
"index": "255",
"unknown1": "100680946"
},
"1: l_hintdung": {
"type": "Location",
"value": "3",
"not": "False",
"index": "3",
"unknown1": "14"
},
"2: n_alchemist": {
"type": "Npc",
"value": "3",
"not": "False",
"index": "3",
"unknown1": "1156761600"
},
"3: ": {
"type": "Item",
"value": "-1",
"not": "False",
"index": "255",
"unknown1": "1997668352"
}
},
"messageId": -1,
"flags": 0,
"lastUpdate": 111
},
"10:  => RemoveTopics (n_local)": {
"opCode": 11,
"argCount": 4,
"arguments:": {
"0: _": {
"type": "State",
"value": "-1",
"not": "False",
"index": "255",
"unknown1": "100680946"
},
"1: ": {
"type": "Location",
"value": "-1",
"not": "False",
"index": "255",
"unknown1": "14"
},
"2: n_local": {
"type": "Npc",
"value": "5",
"not": "False",
"index": "5",
"unknown1": "1156761600"
},
"3: ": {
"type": "Item",
"value": "-1",
"not": "False",
"index": "255",
"unknown1": "1997668352"
}
},
"messageId": -1,
"flags": 0,
"lastUpdate": 111
},
"11:  => RemoveTopics (l_mapdung, n_priest)": {
"opCode": 11,
"argCount": 4,
"arguments:": {
"0: _": {
"type": "State",
"value": "-1",
"not": "False",
"index": "255",
"unknown1": "100680946"
},
"1: l_mapdung": {
"type": "Location",
"value": "0",
"not": "False",
"index": "0",
"unknown1": "14"
},
"2: n_priest": {
"type": "Npc",
"value": "0",
"not": "False",
"index": "0",
"unknown1": "1156761600"
},
"3: ": {
"type": "Item",
"value": "-1",
"not": "False",
"index": "255",
"unknown1": "1997668352"
}
},
"messageId": -1,
"flags": 0,
"lastUpdate": 111
},
"12:  => PlaceItemAt (i_00000634, l_hintdung)": {
"opCode": 0,
"argCount": 3,
"arguments:": {
"0: _": {
"type": "State",
"value": "-1",
"not": "False",
"index": "255",
"unknown1": "100680946"
},
"1: i_00000634": {
"type": "Item",
"value": "3",
"not": "False",
"index": "3",
"unknown1": "14"
},
"2: l_hintdung": {
"type": "Location",
"value": "3",
"not": "False",
"index": "3",
"unknown1": "1156761600"
}
},
"messageId": -1,
"flags": 0,
"lastUpdate": 111
},
"13:  => PlaceItemAt (i_map, l_mapdung)": {
"opCode": 0,
"argCount": 3,
"arguments:": {
"0: _": {
"type": "State",
"value": "-1",
"not": "False",
"index": "255",
"unknown1": "100680946"
},
"1: i_map": {
"type": "Item",
"value": "2",
"not": "False",
"index": "2",
"unknown1": "14"
},
"2: l_mapdung": {
"type": "Location",
"value": "0",
"not": "False",
"index": "0",
"unknown1": "1156761600"
}
},
"messageId": -1,
"flags": 0,
"lastUpdate": 111
},
"14:  => PlaceNpcAt (n_child, l_childhouse)": {
"opCode": 30,
"argCount": 3,
"arguments:": {
"0: _": {
"type": "State",
"value": "-1",
"not": "False",
"index": "255",
"unknown1": "100680946"
},
"1: n_child": {
"type": "Npc",
"value": "1",
"not": "False",
"index": "1",
"unknown1": "14"
},
"2: l_childhouse": {
"type": "Location",
"value": "2",
"not": "False",
"index": "2",
"unknown1": "1156761600"
}
},
"messageId": -1,
"flags": 0,
"lastUpdate": 111
},
"15:  >> WhenTimerExpires (t_00006cc3): set s_0": {
"opCode": 12,
"argCount": 2,
"arguments:": {
"0: s_6": {
"type": "State",
"value": "6",
"not": "False",
"index": "6",
"unknown1": "100680946"
},
"1: t_00006cc3": {
"type": "Timer",
"value": "0",
"not": "False",
"index": "0",
"unknown1": "14"
}
},
"messageId": -1,
"flags": 0,
"lastUpdate": 111
},
"16:  >> When (s_6): set s_18": {
"opCode": 52,
"argCount": 5,
"arguments:": {
"0: s_18": {
"type": "State",
"value": "18",
"not": "False",
"index": "18",
"unknown1": "100680946"
},
"1: s_6": {
"type": "State",
"value": "6",
"not": "False",
"index": "6",
"unknown1": "14"
},
"2: ": {
"type": "State",
"value": "-2",
"not": "False",
"index": "254",
"unknown1": "1156761600"
},
"3: ": {
"type": "State",
"value": "-2",
"not": "False",
"index": "254",
"unknown1": "1997668352"
},
"4: ": {
"type": "State",
"value": "-2",
"not": "False",
"index": "254",
"unknown1": "17694720"
}
},
"messageId": -1,
"flags": 0,
"lastUpdate": 111
},
"17:  >> When (s_14): set s_19": {
"opCode": 52,
"argCount": 5,
"arguments:": {
"0: s_19": {
"type": "State",
"value": "19",
"not": "False",
"index": "19",
"unknown1": "100680946"
},
"1: s_14": {
"type": "State",
"value": "14",
"not": "False",
"index": "14",
"unknown1": "14"
},
"2: ": {
"type": "State",
"value": "-2",
"not": "False",
"index": "254",
"unknown1": "1156761600"
},
"3: ": {
"type": "State",
"value": "-2",
"not": "False",
"index": "254",
"unknown1": "1997668352"
},
"4: ": {
"type": "State",
"value": "-2",
"not": "False",
"index": "254",
"unknown1": "17694720"
}
},
"messageId": -1,
"flags": 0,
"lastUpdate": 111
},
"18: s_19 => Unset (s_18)": {
"opCode": 7,
"argCount": 5,
"arguments:": {
"0: s_19": {
"type": "State",
"value": "19",
"not": "False",
"index": "19",
"unknown1": "100680946"
},
"1: s_18": {
"type": "State",
"value": "18",
"not": "False",
"index": "18",
"unknown1": "14"
},
"2: ": {
"type": "State",
"value": "-2",
"not": "False",
"index": "254",
"unknown1": "1156761600"
},
"3: ": {
"type": "State",
"value": "-2",
"not": "False",
"index": "254",
"unknown1": "1997668352"
},
"4: ": {
"type": "State",
"value": "-2",
"not": "False",
"index": "254",
"unknown1": "17694720"
}
},
"messageId": -1,
"flags": 0,
"lastUpdate": 111
},
"19: s_18 => CreateFoe(m_0003808b, 79, 20%, 20)": {
"opCode": 9,
"argCount": 5,
"arguments:": {
"0: s_18": {
"type": "State",
"value": "18",
"not": "False",
"index": "18",
"unknown1": "100680946"
},
"1: m_0003808b": {
"type": "Mob",
"value": "0",
"not": "False",
"index": "0",
"unknown1": "14"
},
"2: 79": {
"type": "Value",
"value": "79",
"not": "False",
"index": "0",
"unknown1": "1156761600"
},
"3: 20": {
"type": "Value",
"value": "20",
"not": "False",
"index": "0",
"unknown1": "1997668352"
},
"4: 30": {
"type": "Value",
"value": "30",
"not": "False",
"index": "0",
"unknown1": "17694720"
}
},
"messageId": -1,
"flags": 0,
"lastUpdate": 111
},
"20:  >> WhenPlayerHasItems (i_letter): set s_9": {
"opCode": 70,
"argCount": 5,
"arguments:": {
"0: _": {
"type": "State",
"value": "-1",
"not": "False",
"index": "255",
"unknown1": "100680946"
},
"1: s_9": {
"type": "State",
"value": "9",
"not": "False",
"index": "9",
"unknown1": "14"
},
"2: i_letter": {
"type": "Item",
"value": "0",
"not": "False",
"index": "0",
"unknown1": "1156761600"
},
"3: ": {
"type": "Item",
"value": "-1",
"not": "False",
"index": "255",
"unknown1": "1997668352"
},
"4: ": {
"type": "Item",
"value": "-1",
"not": "False",
"index": "255",
"unknown1": "17694720"
}
},
"messageId": -1,
"flags": 0,
"lastUpdate": 111
},
"21: s_7 => TriggerOnMobHurtByPlayer (m_0003808b) [Msg 1040]": {
"opCode": 21,
"argCount": 2,
"arguments:": {
"0: s_7": {
"type": "State",
"value": "7",
"not": "False",
"index": "7",
"unknown1": "100680946"
},
"1: m_0003808b": {
"type": "Mob",
"value": "0",
"not": "False",
"index": "0",
"unknown1": "14"
}
},
"messageId": 1040,
"flags": 0,
"lastUpdate": 111
},
"22:  >> WhenItemIsUsed (i_letter): set s_1": {
"opCode": 57,
"argCount": 3,
"arguments:": {
"0: _": {
"type": "State",
"value": "-1",
"not": "False",
"index": "255",
"unknown1": "100680946"
},
"1: s_1": {
"type": "State",
"value": "1",
"not": "False",
"index": "1",
"unknown1": "14"
},
"2: i_letter": {
"type": "Item",
"value": "0",
"not": "False",
"index": "0",
"unknown1": "1156761600"
}
},
"messageId": -1,
"flags": 0,
"lastUpdate": 111
},
"23: s_1 => AddTopics (n_shaman)": {
"opCode": 10,
"argCount": 4,
"arguments:": {
"0: s_1": {
"type": "State",
"value": "1",
"not": "False",
"index": "1",
"unknown1": "100680946"
},
"1: ": {
"type": "Location",
"value": "-1",
"not": "False",
"index": "255",
"unknown1": "14"
},
"2: n_shaman": {
"type": "Npc",
"value": "2",
"not": "False",
"index": "2",
"unknown1": "1156761600"
},
"3: ": {
"type": "Item",
"value": "-1",
"not": "False",
"index": "255",
"unknown1": "1997668352"
}
},
"messageId": -1,
"flags": 0,
"lastUpdate": 111
},
"24: s_1 => AddTopics (n_priest)": {
"opCode": 10,
"argCount": 4,
"arguments:": {
"0: s_1": {
"type": "State",
"value": "1",
"not": "False",
"index": "1",
"unknown1": "100680946"
},
"1: ": {
"type": "Location",
"value": "-1",
"not": "False",
"index": "255",
"unknown1": "14"
},
"2: n_priest": {
"type": "Npc",
"value": "0",
"not": "False",
"index": "0",
"unknown1": "1156761600"
},
"3: ": {
"type": "Item",
"value": "-1",
"not": "False",
"index": "255",
"unknown1": "1997668352"
}
},
"messageId": -1,
"flags": 0,
"lastUpdate": 111
},
"25: s_0 => TriggerOnClickNpc (n_priest)": {
"opCode": 28,
"argCount": 2,
"arguments:": {
"0: s_0": {
"type": "State",
"value": "0",
"not": "False",
"index": "0",
"unknown1": "100680946"
},
"1: n_priest": {
"type": "Npc",
"value": "0",
"not": "False",
"index": "0",
"unknown1": "14"
}
},
"messageId": -1,
"flags": 0,
"lastUpdate": 111
},
"26: s_0 => Say (1021)": {
"opCode": 51,
"argCount": 1,
"arguments:": {
"0: s_0": {
"type": "State",
"value": "0",
"not": "False",
"index": "0",
"unknown1": "100680946"
}
},
"messageId": 1021,
"flags": 0,
"lastUpdate": 111
},
"27: s_0 => PromptYesNo (s_3, s_4, 1030)": {
"opCode": 29,
"argCount": 4,
"arguments:": {
"0: s_0": {
"type": "State",
"value": "0",
"not": "False",
"index": "0",
"unknown1": "100680946"
},
"1: s_3": {
"type": "State",
"value": "3",
"not": "False",
"index": "3",
"unknown1": "14"
},
"2: s_4": {
"type": "State",
"value": "4",
"not": "False",
"index": "4",
"unknown1": "1156761600"
},
"3: 1030": {
"type": "Value",
"value": "1030",
"not": "False",
"index": "0",
"unknown1": "1997668352"
}
},
"messageId": -1,
"flags": 0,
"lastUpdate": 111
},
"28: s_3 => Say (1022)": {
"opCode": 51,
"argCount": 1,
"arguments:": {
"0: s_3": {
"type": "State",
"value": "3",
"not": "False",
"index": "3",
"unknown1": "100680946"
}
},
"messageId": 1022,
"flags": 0,
"lastUpdate": 111
},
"29: s_3 => CreateLogEntry (1051, 1)": {
"opCode": 23,
"argCount": 3,
"arguments:": {
"0: s_3": {
"type": "State",
"value": "3",
"not": "False",
"index": "3",
"unknown1": "100680946"
},
"1: 1051": {
"type": "Value",
"value": "1051",
"not": "False",
"index": "0",
"unknown1": "14"
},
"2: 1": {
"type": "Value",
"value": "1",
"not": "False",
"index": "0",
"unknown1": "1156761600"
}
},
"messageId": -1,
"flags": 0,
"lastUpdate": 111
},
"30: s_4 => Say (1023)": {
"opCode": 51,
"argCount": 1,
"arguments:": {
"0: s_4": {
"type": "State",
"value": "4",
"not": "False",
"index": "4",
"unknown1": "100680946"
}
},
"messageId": 1023,
"flags": 0,
"lastUpdate": 111
},
"31: s_4 => CreateLogEntry (1052, 1)": {
"opCode": 23,
"argCount": 3,
"arguments:": {
"0: s_4": {
"type": "State",
"value": "4",
"not": "False",
"index": "4",
"unknown1": "100680946"
},
"1: 1052": {
"type": "Value",
"value": "1052",
"not": "False",
"index": "0",
"unknown1": "14"
},
"2: 1": {
"type": "Value",
"value": "1",
"not": "False",
"index": "0",
"unknown1": "1156761600"
}
},
"messageId": -1,
"flags": 0,
"lastUpdate": 111
},
"32: s_3 => AddTopics (n_alchemist)": {
"opCode": 10,
"argCount": 4,
"arguments:": {
"0: s_3": {
"type": "State",
"value": "3",
"not": "False",
"index": "3",
"unknown1": "100680946"
},
"1: ": {
"type": "Location",
"value": "-1",
"not": "False",
"index": "255",
"unknown1": "14"
},
"2: n_alchemist": {
"type": "Npc",
"value": "3",
"not": "False",
"index": "3",
"unknown1": "1156761600"
},
"3: ": {
"type": "Item",
"value": "-1",
"not": "False",
"index": "255",
"unknown1": "1997668352"
}
},
"messageId": -1,
"flags": 0,
"lastUpdate": 111
},
"33: s_3 => AddTopics (n_father)": {
"opCode": 10,
"argCount": 4,
"arguments:": {
"0: s_3": {
"type": "State",
"value": "3",
"not": "False",
"index": "3",
"unknown1": "100680946"
},
"1: ": {
"type": "Location",
"value": "-1",
"not": "False",
"index": "255",
"unknown1": "14"
},
"2: n_father": {
"type": "Npc",
"value": "4",
"not": "False",
"index": "4",
"unknown1": "1156761600"
},
"3: ": {
"type": "Item",
"value": "-1",
"not": "False",
"index": "255",
"unknown1": "1997668352"
}
},
"messageId": -1,
"flags": 0,
"lastUpdate": 111
},
"34: s_4 => AddLocationToMap (l_hintdung)": {
"opCode": 19,
"argCount": 2,
"arguments:": {
"0: s_4": {
"type": "State",
"value": "4",
"not": "False",
"index": "4",
"unknown1": "100680946"
},
"1: l_hintdung": {
"type": "Location",
"value": "3",
"not": "False",
"index": "3",
"unknown1": "14"
}
},
"messageId": -1,
"flags": 0,
"lastUpdate": 111
},
"35:  >> WhenItemIsUsed (i_00000634): set s_16": {
"opCode": 57,
"argCount": 3,
"arguments:": {
"0: _": {
"type": "State",
"value": "-1",
"not": "False",
"index": "255",
"unknown1": "100680946"
},
"1: s_16": {
"type": "State",
"value": "16",
"not": "False",
"index": "16",
"unknown1": "14"
},
"2: i_00000634": {
"type": "Item",
"value": "3",
"not": "False",
"index": "3",
"unknown1": "1156761600"
}
},
"messageId": -1,
"flags": 0,
"lastUpdate": 111
},
"36: s_16 => AddLocationToMap (l_mapdung)": {
"opCode": 19,
"argCount": 2,
"arguments:": {
"0: s_16": {
"type": "State",
"value": "16",
"not": "False",
"index": "16",
"unknown1": "100680946"
},
"1: l_mapdung": {
"type": "Location",
"value": "0",
"not": "False",
"index": "0",
"unknown1": "14"
}
},
"messageId": -1,
"flags": 0,
"lastUpdate": 111
},
"37: s_16 => CreateLogEntry (1053, 2)": {
"opCode": 23,
"argCount": 3,
"arguments:": {
"0: s_16": {
"type": "State",
"value": "16",
"not": "False",
"index": "16",
"unknown1": "100680946"
},
"1: 1053": {
"type": "Value",
"value": "1053",
"not": "False",
"index": "0",
"unknown1": "14"
},
"2: 2": {
"type": "Value",
"value": "2",
"not": "False",
"index": "0",
"unknown1": "1156761600"
}
},
"messageId": -1,
"flags": 0,
"lastUpdate": 111
},
"38: s_11 => TakePlayerGold (s_12, 1000, n_alchemist)": {
"opCode": 71,
"argCount": 4,
"arguments:": {
"0: s_11": {
"type": "State",
"value": "11",
"not": "False",
"index": "11",
"unknown1": "100680946"
},
"1: s_12": {
"type": "State",
"value": "12",
"not": "False",
"index": "12",
"unknown1": "14"
},
"2: 1000": {
"type": "Value",
"value": "1000",
"not": "False",
"index": "0",
"unknown1": "1156761600"
},
"3: n_alchemist": {
"type": "Npc",
"value": "3",
"not": "False",
"index": "3",
"unknown1": "1997668352"
}
},
"messageId": -1,
"flags": 0,
"lastUpdate": 111
},
"39: s_11 => Say (1024)": {
"opCode": 51,
"argCount": 1,
"arguments:": {
"0: s_11": {
"type": "State",
"value": "11",
"not": "False",
"index": "11",
"unknown1": "100680946"
}
},
"messageId": 1024,
"flags": 0,
"lastUpdate": 111
},
"40: s_12 => Say (1025)": {
"opCode": 51,
"argCount": 1,
"arguments:": {
"0: s_12": {
"type": "State",
"value": "12",
"not": "False",
"index": "12",
"unknown1": "100680946"
}
},
"messageId": 1025,
"flags": 0,
"lastUpdate": 111
},
"41: s_11 => PlaceItemOnCharacter (i_00000c7e)": {
"opCode": 26,
"argCount": 3,
"arguments:": {
"0: s_11": {
"type": "State",
"value": "11",
"not": "False",
"index": "11",
"unknown1": "100680946"
},
"1: i_00000c7e": {
"type": "Item",
"value": "1",
"not": "False",
"index": "1",
"unknown1": "14"
},
"2: ": {
"type": "Npc",
"value": "-1",
"not": "False",
"index": "255",
"unknown1": "1156761600"
}
},
"messageId": -1,
"flags": 0,
"lastUpdate": 111
},
"42: s_12 => Unset (s_12, s_11)": {
"opCode": 7,
"argCount": 5,
"arguments:": {
"0: s_12": {
"type": "State",
"value": "12",
"not": "False",
"index": "12",
"unknown1": "100680946"
},
"1: s_12": {
"type": "State",
"value": "12",
"not": "False",
"index": "12",
"unknown1": "14"
},
"2: s_11": {
"type": "State",
"value": "11",
"not": "False",
"index": "11",
"unknown1": "1156761600"
},
"3: ": {
"type": "State",
"value": "-2",
"not": "False",
"index": "254",
"unknown1": "1997668352"
},
"4: ": {
"type": "State",
"value": "-2",
"not": "False",
"index": "254",
"unknown1": "17694720"
}
},
"messageId": -1,
"flags": 0,
"lastUpdate": 111
},
"43: s_13 => TriggerOnClickNpc (n_local)": {
"opCode": 28,
"argCount": 2,
"arguments:": {
"0: s_13": {
"type": "State",
"value": "13",
"not": "False",
"index": "13",
"unknown1": "100680946"
},
"1: n_local": {
"type": "Npc",
"value": "5",
"not": "False",
"index": "5",
"unknown1": "14"
}
},
"messageId": -1,
"flags": 0,
"lastUpdate": 111
},
"44: s_13 => Say (1026)": {
"opCode": 51,
"argCount": 1,
"arguments:": {
"0: s_13": {
"type": "State",
"value": "13",
"not": "False",
"index": "13",
"unknown1": "100680946"
}
},
"messageId": 1026,
"flags": 0,
"lastUpdate": 111
},
"45: s_13 => AddTopics (n_child)": {
"opCode": 10,
"argCount": 4,
"arguments:": {
"0: s_13": {
"type": "State",
"value": "13",
"not": "False",
"index": "13",
"unknown1": "100680946"
},
"1: ": {
"type": "Location",
"value": "-1",
"not": "False",
"index": "255",
"unknown1": "14"
},
"2: n_child": {
"type": "Npc",
"value": "1",
"not": "False",
"index": "1",
"unknown1": "1156761600"
},
"3: ": {
"type": "Item",
"value": "-1",
"not": "False",
"index": "255",
"unknown1": "1997668352"
}
},
"messageId": -1,
"flags": 0,
"lastUpdate": 111
},
"46: s_13 => CreateLogEntry (1054, 2)": {
"opCode": 23,
"argCount": 3,
"arguments:": {
"0: s_13": {
"type": "State",
"value": "13",
"not": "False",
"index": "13",
"unknown1": "100680946"
},
"1: 1054": {
"type": "Value",
"value": "1054",
"not": "False",
"index": "0",
"unknown1": "14"
},
"2: 2": {
"type": "Value",
"value": "2",
"not": "False",
"index": "0",
"unknown1": "1156761600"
}
},
"messageId": -1,
"flags": 0,
"lastUpdate": 111
},
"47:  >> WhenGivingItemToNpc (i_00000c7e, n_child): set s_8": {
"opCode": 1,
"argCount": 3,
"arguments:": {
"0: s_8": {
"type": "State",
"value": "8",
"not": "False",
"index": "8",
"unknown1": "100680946"
},
"1: i_00000c7e": {
"type": "Item",
"value": "1",
"not": "False",
"index": "1",
"unknown1": "14"
},
"2: n_child": {
"type": "Npc",
"value": "1",
"not": "False",
"index": "1",
"unknown1": "1156761600"
}
},
"messageId": -1,
"flags": 0,
"lastUpdate": 111
},
"48: s_8 => Say (1027)": {
"opCode": 51,
"argCount": 1,
"arguments:": {
"0: s_8": {
"type": "State",
"value": "8",
"not": "False",
"index": "8",
"unknown1": "100680946"
}
},
"messageId": 1027,
"flags": 0,
"lastUpdate": 111
},
"49: s_8 => PromptYesNo (s_14, s_15, 1028)": {
"opCode": 29,
"argCount": 4,
"arguments:": {
"0: s_8": {
"type": "State",
"value": "8",
"not": "False",
"index": "8",
"unknown1": "100680946"
},
"1: s_14": {
"type": "State",
"value": "14",
"not": "False",
"index": "14",
"unknown1": "14"
},
"2: s_15": {
"type": "State",
"value": "15",
"not": "False",
"index": "15",
"unknown1": "1156761600"
},
"3: 1028": {
"type": "Value",
"value": "1028",
"not": "False",
"index": "0",
"unknown1": "1997668352"
}
},
"messageId": -1,
"flags": 0,
"lastUpdate": 111
},
"50: s_15 => PlaceItemOnCharacter (i_00000c7e)": {
"opCode": 26,
"argCount": 3,
"arguments:": {
"0: s_15": {
"type": "State",
"value": "15",
"not": "False",
"index": "15",
"unknown1": "100680946"
},
"1: i_00000c7e": {
"type": "Item",
"value": "1",
"not": "False",
"index": "1",
"unknown1": "14"
},
"2: ": {
"type": "Npc",
"value": "-1",
"not": "False",
"index": "255",
"unknown1": "1156761600"
}
},
"messageId": -1,
"flags": 0,
"lastUpdate": 111
},
"51: s_14 => CureLycanthropy ()": {
"opCode": 59,
"argCount": 1,
"arguments:": {
"0: s_14": {
"type": "State",
"value": "14",
"not": "False",
"index": "14",
"unknown1": "100680946"
}
},
"messageId": -1,
"flags": 0,
"lastUpdate": 111
},
"52: s_14 => AdjustLegalReputation (-10)": {
"opCode": 65,
"argCount": 2,
"arguments:": {
"0: s_14": {
"type": "State",
"value": "14",
"not": "False",
"index": "14",
"unknown1": "100680946"
},
"1: -10": {
"type": "Value",
"value": "-10",
"not": "False",
"index": "0",
"unknown1": "14"
}
},
"messageId": -1,
"flags": 0,
"lastUpdate": 111
},
"53: s_14 => QuestSuccess ()": {
"opCode": 4,
"argCount": 5,
"arguments:": {
"0: s_14": {
"type": "State",
"value": "14",
"not": "False",
"index": "14",
"unknown1": "100680946"
},
"1: ": {
"type": "Item",
"value": "-1",
"not": "False",
"index": "255",
"unknown1": "14"
},
"2: ": {
"type": "Item",
"value": "-1",
"not": "False",
"index": "255",
"unknown1": "1156761600"
},
"3: ": {
"type": "Item",
"value": "-1",
"not": "False",
"index": "255",
"unknown1": "1997668352"
},
"4: ": {
"type": "Item",
"value": "-1",
"not": "False",
"index": "255",
"unknown1": "17694720"
}
},
"messageId": -1,
"flags": 0,
"lastUpdate": 111
},
"54: s_14 => HideNpc (n_child)": {
"opCode": 46,
"argCount": 2,
"arguments:": {
"0: s_14": {
"type": "State",
"value": "14",
"not": "False",
"index": "14",
"unknown1": "100680946"
},
"1: n_child": {
"type": "Npc",
"value": "1",
"not": "False",
"index": "1",
"unknown1": "14"
}
},
"messageId": -1,
"flags": 0,
"lastUpdate": 111
},
"55: s_14 => PlaceMobAtLocation (m_wereboar, l_childhouse)": {
"opCode": 22,
"argCount": 3,
"arguments:": {
"0: s_14": {
"type": "State",
"value": "14",
"not": "False",
"index": "14",
"unknown1": "100680946"
},
"1: m_wereboar": {
"type": "Mob",
"value": "1",
"not": "False",
"index": "1",
"unknown1": "14"
},
"2: l_childhouse": {
"type": "Location",
"value": "2",
"not": "False",
"index": "2",
"unknown1": "1156761600"
}
},
"messageId": -1,
"flags": 0,
"lastUpdate": 111
},
"56: s_17 => TriggerOnMobKills (m_wereboar, 1)": {
"opCode": 2,
"argCount": 3,
"arguments:": {
"0: s_17": {
"type": "State",
"value": "17",
"not": "False",
"index": "17",
"unknown1": "100680946"
},
"1: m_wereboar": {
"type": "Mob",
"value": "1",
"not": "False",
"index": "1",
"unknown1": "14"
},
"2: 1": {
"type": "Value",
"value": "1",
"not": "False",
"index": "0",
"unknown1": "1156761600"
}
},
"messageId": -1,
"flags": 0,
"lastUpdate": 111
},
"57: s_17 => AdjustLegalReputation (-20)": {
"opCode": 65,
"argCount": 2,
"arguments:": {
"0: s_17": {
"type": "State",
"value": "17",
"not": "False",
"index": "17",
"unknown1": "100680946"
},
"1: -20": {
"type": "Value",
"value": "-20",
"not": "False",
"index": "0",
"unknown1": "14"
}
},
"messageId": -1,
"flags": 0,
"lastUpdate": 111
},
"58: s_5 => MakePermanent (i_map)": {
"opCode": 54,
"argCount": 2,
"arguments:": {
"0: s_5": {
"type": "State",
"value": "5",
"not": "False",
"index": "5",
"unknown1": "100680946"
},
"1: i_map": {
"type": "Item",
"value": "2",
"not": "False",
"index": "2",
"unknown1": "14"
}
},
"messageId": -1,
"flags": 0,
"lastUpdate": 111
},
"59: s_5 => EndQuest ()": {
"opCode": 6,
"argCount": 1,
"arguments:": {
"0: s_5": {
"type": "State",
"value": "5",
"not": "False",
"index": "5",
"unknown1": "100680946"
}
},
"messageId": -1,
"flags": 0,
"lastUpdate": 111
}
}
,"states: [20]": {
" 0: s_000dddc2": {
"variable": "s_000dddc2",
"isGlobal": false,
"globalIndex": 0,
"index": 0
},
" 1: s_readletter": {
"variable": "s_readletter",
"isGlobal": false,
"globalIndex": 0,
"index": 1
},
" 2: s_000033b2": {
"variable": "s_000033b2",
"isGlobal": false,
"globalIndex": 0,
"index": 2
},
" 3: s_0001a077": {
"variable": "s_0001a077",
"isGlobal": false,
"globalIndex": 0,
"index": 3
},
" 4: s_00003386": {
"variable": "s_00003386",
"isGlobal": false,
"globalIndex": 0,
"index": 4
},
" 5: s_00006cc3": {
"variable": "s_00006cc3",
"isGlobal": false,
"globalIndex": 0,
"index": 5
},
" 6: s_huntstart": {
"variable": "s_huntstart",
"isGlobal": false,
"globalIndex": 0,
"index": 6
},
" 7: s_0000d44c": {
"variable": "s_0000d44c",
"isGlobal": false,
"globalIndex": 0,
"index": 7
},
" 8: s_0000d21e": {
"variable": "s_0000d21e",
"isGlobal": false,
"globalIndex": 0,
"index": 8
},
" 9: s_0000cc1e": {
"variable": "s_0000cc1e",
"isGlobal": false,
"globalIndex": 0,
"index": 9
},
"10: s_00001bde": {
"variable": "s_00001bde",
"isGlobal": false,
"globalIndex": 0,
"index": 10
},
"11: s_npc": {
"variable": "s_npc",
"isGlobal": false,
"globalIndex": 0,
"index": 11
},
"12: s_00000d53": {
"variable": "s_00000d53",
"isGlobal": false,
"globalIndex": 0,
"index": 12
},
"13: s_0001aaa5": {
"variable": "s_0001aaa5",
"isGlobal": false,
"globalIndex": 0,
"index": 13
},
"14: s_0007141e": {
"variable": "s_0007141e",
"isGlobal": false,
"globalIndex": 0,
"index": 14
},
"15: s_00035f4d": {
"variable": "s_00035f4d",
"isGlobal": false,
"globalIndex": 0,
"index": 15
},
"16: s_00006ad4": {
"variable": "s_00006ad4",
"isGlobal": false,
"globalIndex": 0,
"index": 16
},
"17: s_0000d450": {
"variable": "s_0000d450",
"isGlobal": false,
"globalIndex": 0,
"index": 17
},
"18: s_00001ad3": {
"variable": "s_00001ad3",
"isGlobal": false,
"globalIndex": 0,
"index": 18
},
"19: s_000071c4": {
"variable": "s_000071c4",
"isGlobal": false,
"globalIndex": 0,
"index": 19
}
}
}
