{
"quest info: ": {
"name": "R0C20Y22",
"questType": "Royalty",
"membership": "NonMember",
"reputation": 20,
"delivery": "InPerson",
"childSafe": true,
"questId": 0,
"faction": "None",
"resourceId": 0,
"resourceFileName": "",
"hasDebugInfo": false
}
,"items: [2]": {
" 0: i_reward: Ruby [Gem]": {
"variable": "i_reward",
"nameRaw": "[0x00001B14]",
"rewardType": "Item1",
"category": "Gem",
"itemId": 0,
"textRecordId1": 0,
"textRecordId2": 0,
"index": 0,
"unknown1": "0 [0x00000000]"
},
" 1: i_item: [Jewellery]": {
"variable": "i_item",
"nameRaw": "[0x0000064F]",
"rewardType": "Item1",
"category": "Jewellery",
"itemId": 65535,
"textRecordId1": 0,
"textRecordId2": 0,
"index": 1,
"unknown1": "0 [0x00000000]"
}
}
,"npcs: [3]": {
" 0: n_questgiver:  (type? QuestGiver)": {
"variable": "n_questgiver",
"nameRaw": "[0x0001c18c]",
"unknown1": "[0x00]",
"facePictureIndex": 0,
"npcType": "QuestGiver",
"npcTypeRaw": "21 [0x0015]",
"faction": "None",
"factionRaw": "0 [0x0000]",
"textRecordId1": 1015,
"textRecordId2": 1016,
"index": 0,
"null1": 0
},
" 1: n_contact:  (type? Unknown_3)": {
"variable": "n_contact",
"nameRaw": "[0x000033de]",
"unknown1": "[0x01]",
"facePictureIndex": 0,
"npcType": "Unknown_3",
"npcTypeRaw": "65533 [0xFFFD]",
"faction": "None",
"factionRaw": "0 [0x0000]",
"textRecordId1": 0,
"textRecordId2": 0,
"index": 1,
"null1": 0
},
" 2: n_orsinium:  (faction Orsinium)": {
"variable": "n_orsinium",
"nameRaw": "[0x00006f5b]",
"unknown1": "[0x01]",
"facePictureIndex": 184,
"npcType": "Normal",
"npcTypeRaw": "65535 [0xFFFF]",
"faction": "Orsinium",
"factionRaw": "358 [0x0166]",
"textRecordId1": 1012,
"textRecordId2": 1013,
"index": 2,
"null1": 0
}
}
,"locations: [1]": {
" 0: l_00: Specific OrsiniumCastle": {
"variable": "l_00",
"nameRaw": "[0x00006d6f]",
"generalLocation": "Specific",
"locationType": -1533,
"LocationType": "SpecificLocation",
"fineLocation": 50015,
"knownLocation": "OrsiniumCastle",
"doorSelector": -1,
"textRecordId1": 0,
"textRecordId2": 0,
"index": 0,
"flags": "0 [0x00]",
"objPtr": 0,
"unknown1": "20479 [0x4FFF]"
}
}
,"timers: [1]": {
" 0: t_queston: 1.5 times travel time from here to 'n_orsinium' and then 'n_contact'": {
"variable": "t_queston",
"nameRaw": "[0x000037e4]",
"type": "Relative4",
"typeRaw": "5 [0x05]",
"minimum": "00:00:00",
"maximum": "00:00:00",
"flags1": "2 [00000010]",
"flags2": "3 [11]",
"duration": 0,
"started": 0,
"index": 0
}
}
,"mobs: [2]": {
" 0: m_note: 3 Orc": {
"variable": "m_note",
"nameRaw": "[0X00000679]",
"type": "Orc",
"count": 3,
"null1": 0,
"null2": 0,
"index": 0
},
" 1: m_01: 1 OrcSergeant": {
"variable": "m_01",
"nameRaw": "[0X0006e14b]",
"type": "OrcSergeant",
"count": 1,
"null1": 0,
"null2": 0,
"index": 1
}
}
,"opCodes: [26]": {
" 0:  => RemoveTopics (l_00, n_orsinium)": {
"opCode": 11,
"argCount": 4,
"arguments:": {
"0: _": {
"type": "State",
"value": "-1",
"not": "False",
"index": "255",
"unknown1": "109253858 [0x068314E2]"
},
"1: l_00": {
"type": "Location",
"value": "0",
"not": "False",
"index": "0",
"unknown1": "14 [0x0000000E]"
},
"2: n_orsinium": {
"type": "Npc",
"value": "2",
"not": "False",
"index": "2",
"unknown1": "350423040 [0x14E30800]"
},
"3: ": {
"type": "Item",
"value": "-1",
"not": "False",
"index": "255",
"unknown1": "1736179712 [0x677C0000]"
}
},
"messageId": -1,
"flags": "0 [0x0000]",
"lastUpdate": 1761
},
" 1:  => EnsureNpcLocation (n_orsinium)": {
"opCode": 81,
"argCount": 3,
"arguments:": {
"0: _": {
"type": "State",
"value": "-1",
"not": "False",
"index": "255",
"unknown1": "109253858 [0x068314E2]"
},
"1: ": {
"type": "Location",
"value": "-1",
"not": "False",
"index": "255",
"unknown1": "14 [0x0000000E]"
},
"2: n_orsinium": {
"type": "Npc",
"value": "2",
"not": "False",
"index": "2",
"unknown1": "350423040 [0x14E30800]"
}
},
"messageId": -1,
"flags": "0 [0x0000]",
"lastUpdate": 1761
},
" 2:  => EnsureNpcLocation (n_contact)": {
"opCode": 81,
"argCount": 3,
"arguments:": {
"0: _": {
"type": "State",
"value": "-1",
"not": "False",
"index": "255",
"unknown1": "109253858 [0x068314E2]"
},
"1: ": {
"type": "Location",
"value": "-1",
"not": "False",
"index": "255",
"unknown1": "14 [0x0000000E]"
},
"2: n_contact": {
"type": "Npc",
"value": "1",
"not": "False",
"index": "1",
"unknown1": "350423040 [0x14E30800]"
}
},
"messageId": -1,
"flags": "0 [0x0000]",
"lastUpdate": 1761
},
" 3:  => StartTimer (t_queston); When it expires: set s_queston": {
"opCode": 12,
"argCount": 2,
"arguments:": {
"0: _": {
"type": "State",
"value": "-1",
"not": "False",
"index": "255",
"unknown1": "109253858 [0x068314E2]"
},
"1: t_queston": {
"type": "Timer",
"value": "0",
"not": "False",
"index": "0",
"unknown1": "14 [0x0000000E]"
}
},
"messageId": -1,
"flags": "0 [0x0000]",
"lastUpdate": 1761
},
" 4:  => CreateLogEntry (1010, 0)": {
"opCode": 23,
"argCount": 3,
"arguments:": {
"0: _": {
"type": "State",
"value": "-1",
"not": "False",
"index": "255",
"unknown1": "109253858 [0x068314E2]"
},
"1: 1010": {
"type": "Value",
"value": "1010",
"not": "False",
"index": "0",
"unknown1": "14 [0x0000000E]"
},
"2: 0": {
"type": "Value",
"value": "0",
"not": "False",
"index": "0",
"unknown1": "350423040 [0x14E30800]"
}
},
"messageId": -1,
"flags": "0 [0x0000]",
"lastUpdate": 1761
},
" 5:  => PlaceItemOnCharacter (i_item)": {
"opCode": 26,
"argCount": 3,
"arguments:": {
"0: _": {
"type": "State",
"value": "-1",
"not": "False",
"index": "255",
"unknown1": "109253858 [0x068314E2]"
},
"1: i_item": {
"type": "Item",
"value": "1",
"not": "False",
"index": "1",
"unknown1": "14 [0x0000000E]"
},
"2: ": {
"type": "Npc",
"value": "-1",
"not": "False",
"index": "255",
"unknown1": "350423040 [0x14E30800]"
}
},
"messageId": -1,
"flags": "0 [0x0000]",
"lastUpdate": 1761
},
" 6: not s_rewards1 => CreateFoe(m_01, 10, 35%, 12)": {
"opCode": 9,
"argCount": 5,
"arguments:": {
"0: not s_rewards1": {
"type": "State",
"value": "5",
"not": "True",
"index": "5",
"unknown1": "109253858 [0x068314E2]"
},
"1: m_01": {
"type": "Mob",
"value": "1",
"not": "False",
"index": "1",
"unknown1": "14 [0x0000000E]"
},
"2: 10": {
"type": "Value",
"value": "10",
"not": "False",
"index": "0",
"unknown1": "350423040 [0x14E30800]"
},
"3: 35": {
"type": "Value",
"value": "35",
"not": "False",
"index": "0",
"unknown1": "1736179712 [0x677C0000]"
},
"4: 12": {
"type": "Value",
"value": "12",
"not": "False",
"index": "0",
"unknown1": "17563648 [0x010C0000]"
}
},
"messageId": -1,
"flags": "0 [0x0000]",
"lastUpdate": 1761
},
" 7: not s_rewards1 => CreateFoe(m_note, 5, 35%, 12)": {
"opCode": 9,
"argCount": 5,
"arguments:": {
"0: not s_rewards1": {
"type": "State",
"value": "5",
"not": "True",
"index": "5",
"unknown1": "109253858 [0x068314E2]"
},
"1: m_note": {
"type": "Mob",
"value": "0",
"not": "False",
"index": "0",
"unknown1": "14 [0x0000000E]"
},
"2: 5": {
"type": "Value",
"value": "5",
"not": "False",
"index": "0",
"unknown1": "350423040 [0x14E30800]"
},
"3: 35": {
"type": "Value",
"value": "35",
"not": "False",
"index": "0",
"unknown1": "1736179712 [0x677C0000]"
},
"4: 12": {
"type": "Value",
"value": "12",
"not": "False",
"index": "0",
"unknown1": "17563648 [0x010C0000]"
}
},
"messageId": -1,
"flags": "0 [0x0000]",
"lastUpdate": 1761
},
" 8:  >> IfMobsKilled (m_01, 1): set s_07": {
"opCode": 2,
"argCount": 3,
"arguments:": {
"0: s_07": {
"type": "State",
"value": "7",
"not": "False",
"index": "7",
"unknown1": "109253858 [0x068314E2]"
},
"1: m_01": {
"type": "Mob",
"value": "1",
"not": "False",
"index": "1",
"unknown1": "14 [0x0000000E]"
},
"2: 1": {
"type": "Value",
"value": "1",
"not": "False",
"index": "0",
"unknown1": "350423040 [0x14E30800]"
}
},
"messageId": -1,
"flags": "0 [0x0000]",
"lastUpdate": 1761
},
" 9: s_07 => AddTopics (n_orsinium)": {
"opCode": 10,
"argCount": 4,
"arguments:": {
"0: s_07": {
"type": "State",
"value": "7",
"not": "False",
"index": "7",
"unknown1": "109253858 [0x068314E2]"
},
"1: ": {
"type": "Location",
"value": "-1",
"not": "False",
"index": "255",
"unknown1": "14 [0x0000000E]"
},
"2: n_orsinium": {
"type": "Npc",
"value": "2",
"not": "False",
"index": "2",
"unknown1": "350423040 [0x14E30800]"
},
"3: ": {
"type": "Item",
"value": "-1",
"not": "False",
"index": "255",
"unknown1": "1736179712 [0x677C0000]"
}
},
"messageId": -1,
"flags": "0 [0x0000]",
"lastUpdate": 1761
},
"10: s_07 => Say (1030)": {
"opCode": 51,
"argCount": 1,
"arguments:": {
"0: s_07": {
"type": "State",
"value": "7",
"not": "False",
"index": "7",
"unknown1": "109253858 [0x068314E2]"
}
},
"messageId": 1030,
"flags": "0 [0x0000]",
"lastUpdate": 1761
},
"11:  >> IfNpcClicked (n_orsinium): set s_04": {
"opCode": 28,
"argCount": 2,
"arguments:": {
"0: s_04": {
"type": "State",
"value": "4",
"not": "False",
"index": "4",
"unknown1": "109253858 [0x068314E2]"
},
"1: n_orsinium": {
"type": "Npc",
"value": "2",
"not": "False",
"index": "2",
"unknown1": "14 [0x0000000E]"
}
},
"messageId": -1,
"flags": "0 [0x0000]",
"lastUpdate": 1761
},
"12: s_04 => Say (1020)": {
"opCode": 51,
"argCount": 1,
"arguments:": {
"0: s_04": {
"type": "State",
"value": "4",
"not": "False",
"index": "4",
"unknown1": "109253858 [0x068314E2]"
}
},
"messageId": 1020,
"flags": "0 [0x0000]",
"lastUpdate": 1761
},
"13:  >> IfGivingItemToNpc (i_item, n_orsinium): set s_08": {
"opCode": 1,
"argCount": 3,
"arguments:": {
"0: s_08": {
"type": "State",
"value": "8",
"not": "False",
"index": "8",
"unknown1": "109253858 [0x068314E2]"
},
"1: i_item": {
"type": "Item",
"value": "1",
"not": "False",
"index": "1",
"unknown1": "14 [0x0000000E]"
},
"2: n_orsinium": {
"type": "Npc",
"value": "2",
"not": "False",
"index": "2",
"unknown1": "350423040 [0x14E30800]"
}
},
"messageId": -1,
"flags": "0 [0x0000]",
"lastUpdate": 1761
},
"14: s_08 => PromptYesNo (s_rewards1, s_bookstore, 1021)": {
"opCode": 29,
"argCount": 4,
"arguments:": {
"0: s_08": {
"type": "State",
"value": "8",
"not": "False",
"index": "8",
"unknown1": "109253858 [0x068314E2]"
},
"1: s_rewards1": {
"type": "State",
"value": "5",
"not": "False",
"index": "5",
"unknown1": "14 [0x0000000E]"
},
"2: s_bookstore": {
"type": "State",
"value": "6",
"not": "False",
"index": "6",
"unknown1": "350423040 [0x14E30800]"
},
"3: 1021": {
"type": "Value",
"value": "1021",
"not": "False",
"index": "0",
"unknown1": "1736179712 [0x677C0000]"
}
},
"messageId": -1,
"flags": "0 [0x0000]",
"lastUpdate": 1761
},
"15: s_rewards1 => Say (1022)": {
"opCode": 51,
"argCount": 1,
"arguments:": {
"0: s_rewards1": {
"type": "State",
"value": "5",
"not": "False",
"index": "5",
"unknown1": "109253858 [0x068314E2]"
}
},
"messageId": 1022,
"flags": "0 [0x0000]",
"lastUpdate": 1761
},
"16: s_bookstore => Say (1023)": {
"opCode": 51,
"argCount": 1,
"arguments:": {
"0: s_bookstore": {
"type": "State",
"value": "6",
"not": "False",
"index": "6",
"unknown1": "109253858 [0x068314E2]"
}
},
"messageId": 1023,
"flags": "0 [0x0000]",
"lastUpdate": 1761
},
"17: s_bookstore => PlaceItemOnCharacter (i_item)": {
"opCode": 26,
"argCount": 3,
"arguments:": {
"0: s_bookstore": {
"type": "State",
"value": "6",
"not": "False",
"index": "6",
"unknown1": "109253858 [0x068314E2]"
},
"1: i_item": {
"type": "Item",
"value": "1",
"not": "False",
"index": "1",
"unknown1": "14 [0x0000000E]"
},
"2: ": {
"type": "Npc",
"value": "-1",
"not": "False",
"index": "255",
"unknown1": "350423040 [0x14E30800]"
}
},
"messageId": -1,
"flags": "0 [0x0000]",
"lastUpdate": 1761
},
"18: s_rewards1 => AdjustReputationWithNpc (n_orsinium, 30)": {
"opCode": 61,
"argCount": 3,
"arguments:": {
"0: s_rewards1": {
"type": "State",
"value": "5",
"not": "False",
"index": "5",
"unknown1": "109253858 [0x068314E2]"
},
"1: n_orsinium": {
"type": "Npc",
"value": "2",
"not": "False",
"index": "2",
"unknown1": "14 [0x0000000E]"
},
"2: 30": {
"type": "Value",
"value": "30",
"not": "False",
"index": "0",
"unknown1": "350423040 [0x14E30800]"
}
},
"messageId": -1,
"flags": "0 [0x0000]",
"lastUpdate": 1761
},
"19: s_bookstore => AdjustReputationWithNpc (n_orsinium, -10)": {
"opCode": 61,
"argCount": 3,
"arguments:": {
"0: s_bookstore": {
"type": "State",
"value": "6",
"not": "False",
"index": "6",
"unknown1": "109253858 [0x068314E2]"
},
"1: n_orsinium": {
"type": "Npc",
"value": "2",
"not": "False",
"index": "2",
"unknown1": "14 [0x0000000E]"
},
"2: -10": {
"type": "Value",
"value": "-10",
"not": "False",
"index": "0",
"unknown1": "350423040 [0x14E30800]"
}
},
"messageId": -1,
"flags": "0 [0x0000]",
"lastUpdate": 1761
},
"20:  >> IfGivingItemToNpc (i_item, n_contact): set s_npcclicked": {
"opCode": 1,
"argCount": 3,
"arguments:": {
"0: s_npcclicked": {
"type": "State",
"value": "3",
"not": "False",
"index": "3",
"unknown1": "109253858 [0x068314E2]"
},
"1: i_item": {
"type": "Item",
"value": "1",
"not": "False",
"index": "1",
"unknown1": "14 [0x0000000E]"
},
"2: n_contact": {
"type": "Npc",
"value": "1",
"not": "False",
"index": "1",
"unknown1": "350423040 [0x14E30800]"
}
},
"messageId": -1,
"flags": "0 [0x0000]",
"lastUpdate": 1761
},
"21: s_npcclicked => QuestSuccess (i_reward)": {
"opCode": 4,
"argCount": 5,
"arguments:": {
"0: s_npcclicked": {
"type": "State",
"value": "3",
"not": "False",
"index": "3",
"unknown1": "109253858 [0x068314E2]"
},
"1: i_reward": {
"type": "Item",
"value": "0",
"not": "False",
"index": "0",
"unknown1": "14 [0x0000000E]"
},
"2: ": {
"type": "Item",
"value": "-1",
"not": "False",
"index": "255",
"unknown1": "350423040 [0x14E30800]"
},
"3: ": {
"type": "Item",
"value": "-1",
"not": "False",
"index": "255",
"unknown1": "1736179712 [0x677C0000]"
},
"4: ": {
"type": "Item",
"value": "-1",
"not": "False",
"index": "255",
"unknown1": "17563648 [0x010C0000]"
}
},
"messageId": -1,
"flags": "0 [0x0000]",
"lastUpdate": 1761
},
"22: s_queston => AdjustReputationWithNpc (n_questgiver, -20)": {
"opCode": 61,
"argCount": 3,
"arguments:": {
"0: s_queston": {
"type": "State",
"value": "2",
"not": "False",
"index": "2",
"unknown1": "109253858 [0x068314E2]"
},
"1: n_questgiver": {
"type": "Npc",
"value": "0",
"not": "False",
"index": "0",
"unknown1": "14 [0x0000000E]"
},
"2: -20": {
"type": "Value",
"value": "-20",
"not": "False",
"index": "0",
"unknown1": "350423040 [0x14E30800]"
}
},
"messageId": -1,
"flags": "0 [0x0000]",
"lastUpdate": 1761
},
"23: s_queston => MakePermanent (i_item)": {
"opCode": 54,
"argCount": 2,
"arguments:": {
"0: s_queston": {
"type": "State",
"value": "2",
"not": "False",
"index": "2",
"unknown1": "109253858 [0x068314E2]"
},
"1: i_item": {
"type": "Item",
"value": "1",
"not": "False",
"index": "1",
"unknown1": "14 [0x0000000E]"
}
},
"messageId": -1,
"flags": "0 [0x0000]",
"lastUpdate": 1761
},
"24: s_npcclicked => EndQuest ()": {
"opCode": 6,
"argCount": 1,
"arguments:": {
"0: s_npcclicked": {
"type": "State",
"value": "3",
"not": "False",
"index": "3",
"unknown1": "109253858 [0x068314E2]"
}
},
"messageId": -1,
"flags": "0 [0x0000]",
"lastUpdate": 1761
},
"25: s_queston => EndQuest ()": {
"opCode": 6,
"argCount": 1,
"arguments:": {
"0: s_queston": {
"type": "State",
"value": "2",
"not": "False",
"index": "2",
"unknown1": "109253858 [0x068314E2]"
}
},
"messageId": -1,
"flags": "0 [0x0000]",
"lastUpdate": 1761
}
}
,"states: [9]": {
" 0: s_pcgetsgold": {
"variable": "s_pcgetsgold",
"nameRaw": "[0x0001aba0]",
"isGlobal": false,
"globalIndex": 0,
"index": 0
},
" 1: s_pchasitem": {
"variable": "s_pchasitem",
"nameRaw": "[0x0000d51f]",
"isGlobal": false,
"globalIndex": 0,
"index": 1
},
" 2: s_queston": {
"variable": "s_queston",
"nameRaw": "[0x000037e4]",
"isGlobal": false,
"globalIndex": 0,
"index": 2
},
" 3: s_npcclicked": {
"variable": "s_npcclicked",
"nameRaw": "[0x0001b042]",
"isGlobal": false,
"globalIndex": 0,
"index": 3
},
" 4: s_04": {
"variable": "s_04",
"nameRaw": "[0x0000dbc1]",
"isGlobal": false,
"globalIndex": 0,
"index": 4
},
" 5: s_rewards1": {
"variable": "s_rewards1",
"nameRaw": "[0x00006d67]",
"isGlobal": false,
"globalIndex": 0,
"index": 5
},
" 6: s_bookstore": {
"variable": "s_bookstore",
"nameRaw": "[0x0000d075]",
"isGlobal": false,
"globalIndex": 0,
"index": 6
},
" 7: s_07": {
"variable": "s_07",
"nameRaw": "[0x00003503]",
"isGlobal": false,
"globalIndex": 0,
"index": 7
},
" 8: s_08": {
"variable": "s_08",
"nameRaw": "[0x0000346b]",
"isGlobal": false,
"globalIndex": 0,
"index": 8
}
}
,"text records: [20]": {
"1000": [
"Ah, %pcf, I am glad you're here.  If you are available for hire, I am looking for  someone to purvey a special _item_ to  an acquaintance of mine. The reward, I think,  you will find to be extremely liberal,  to compensate for the danger of the mission.  Are you interested?"
],
"1001": [
"Really? Too busy, perhaps. That is a shame."
],
"1002": [
"Excellent. Here's the _item_.  Now, _contact_ needs to have it  in ___contact_ in =queston_ days.  That ought to be  plenty of time, I hope.  _contact_ will be  easy to find -- just look for a =contact_  at __contact_.  By the way, you may  encounter some orcs who do not want this shipment  made.  I trust you know how to deal with their kind.  Good luck."
],
"1003": [
"Speed is vital, %pcf.  Orcs have been seen  prowling around ___questgiver_ at night.  You had best get on the road before they  become bolder."
],
"1004": [
"Ah, good to see you %pcf. And the  _item_ too. Excellent. Here's a little  trinket for your trouble. I hope you like  red. Take care of yourself."
],
"1005": [
"_questgiver_ is still in the smuggling business, I hear.",
"I hear the guards chased off a couple of orcs last night.  I wonder  what would bring them into town?"
],
"1006": [
"Someone found a very lovely _item_ around here recently.",
"I hear _questgiver_ is mad as hell at some %ra adventurer."
],
"1007": [
"Some =contact_ was just here, waving around some _item_.",
"Some jewelry store has reported the theft of a big ruby, I hear."
],
"1008": [
"I hear that your mission was a success, %pcf. That's good. Very good.",
"I was pleased to hear of the success of the delivery. What can I do for you?"
],
"1009": [
"You're the courier who couldn't  complete the delivery, yes? Wouldn't  I be a fool to waste my breath on  you again?  That's a rhetorical  question, by the way."
],
"1010": [
"%qdt: _questgiver_ has hired me to deliver a _item_ to someone in ___contact_ named _contact_. %g will meet me at __contact_ in =queston_ days to reward me if I have not already been minced by the orcs who are also after the _item_."
],
"1012": [
"You don't want to have anything to do with that orc-lover from ___orsinium_.",
"_orsinium_ of ___orsinium_?  They say %g actually talks to orcs."
],
"1013": [
"_orsinium_ is well-known in ___orsinium_ as an orc sympathizer.",
"I know for a fact that _orsinium_ is a filthy orc-lover.  I've seen %g2  myself, meeting with the brutes outside of ___orsinium_.  %g should be run out  of town, if you ask me."
],
"1015": [
"_questgiver_ will deny it, but they say %g's in the smuggling business.",
"_questgiver_ is said to be involved in a smuggling ring, bringing in loot  plundered out of old Orsinium."
],
"1016": [
"_questgiver_ will bring the orcs down on all of us if he keeps dealing in  plunder from Orsinium.  _orsinium_ has accused _questgiver_ publicly,  but nothing's been done about it, of course.",
"I don't know where _questgiver_ gets it from, but I've seen %g2 wearing  some exquisite antique jewelry lately.  Ancient Orsinium craftsmanship, if  I'm not mistaken."
],
"1020": [
"I'm glad you sought me out, %pcn.  You should know that the _item_ you are carrying  was stolen from Orsinium, the ancient capital of the orcs.  _questgiver_, like most people, treats orcs  as beneath contempt, hence they are forced to resort to  violence to recover their stolen property.  However, I hope  that you are more enlightened than your employer.  If you  give me the _item_, I will see that it is returned to its  rightful owners."
],
"1021": [
"Do you give the _item_?"
],
"1022": [
"I'm glad I was right about you.  Thank you,  %pcf.  We will not forget this."
],
"1023": [
"That is most regrettable.  Well, we all  have our reasons.  I hope you can live  with this decision."
],
"1030": [
"As the orc crumples to the ground, it gasps in  a barely comprehensible accent,  \"_orsinium_ ... go ... _orsinium_ ...\""
]
}
}
