{
"quest info: ": {
"name": "S0000002",
"questType": "Main",
"membership": "None",
"reputation": 0,
"delivery": "Unknown",
"childSafe": true,
"questId": 0,
"faction": "None",
"resourceId": 0,
"resourceFileName": "",
"hasDebugInfo": false
}
,"items: [6]": {
" 0: i_00: Parchment [Usable] [1010]": {
"variable": "i_00",
"nameRaw": "[0x0000C97A]",
"rewardType": "Item1",
"category": "Usable",
"itemId": 5,
"textRecordId1": 0,
"textRecordId2": 1010,
"index": 0,
"unknown1": "0 [0x00000000]"
},
" 1: i_magicitem: [MagicItem]": {
"variable": "i_magicitem",
"nameRaw": "[0x0000D0DF]",
"rewardType": "Item1",
"category": "MagicItem",
"itemId": 65535,
"textRecordId1": 0,
"textRecordId2": 0,
"index": 1,
"unknown1": "0 [0x00000000]"
},
" 2: i_02: Parchment [Usable] [1024]": {
"variable": "i_02",
"nameRaw": "[0x00006E1B]",
"rewardType": "Item1",
"category": "Usable",
"itemId": 5,
"textRecordId1": 0,
"textRecordId2": 1024,
"index": 2,
"unknown1": "0 [0x00000000]"
},
" 3: i_03: Parchment [Usable] [1026]": {
"variable": "i_03",
"nameRaw": "[0x000065BC]",
"rewardType": "Item1",
"category": "Usable",
"itemId": 5,
"textRecordId1": 0,
"textRecordId2": 1026,
"index": 3,
"unknown1": "0 [0x00000000]"
},
" 4: i_04: Parchment [Usable] [1040]": {
"variable": "i_04",
"nameRaw": "[0x001A85FC]",
"rewardType": "Item1",
"category": "Usable",
"itemId": 5,
"textRecordId1": 0,
"textRecordId2": 1040,
"index": 4,
"unknown1": "0 [0x00000000]"
},
" 5: i_6: 100 - 100 gold": {
"variable": "i_6",
"nameRaw": "[0x41000006]",
"rewardType": "Gold",
"category": "100",
"itemId": 100,
"textRecordId1": 0,
"textRecordId2": 0,
"index": 5,
"unknown1": "0 [0x00000000]"
}
}
,"npcs: [3]": {
" 0: n_00:  (type? Permanent) (faction Prince_Helseth)": {
"variable": "n_00",
"nameRaw": "[0x000033dc]",
"unknown1": "[0x01]",
"facePictureIndex": 0,
"npcType": "Permanent",
"npcTypeRaw": "65528 [0xFFF8]",
"faction": "Prince_Helseth",
"factionRaw": "393 [0x0189]",
"textRecordId1": 0,
"textRecordId2": 0,
"index": 0,
"null1": 0
},
" 1: n_01:  (faction Lord_Castellian)": {
"variable": "n_01",
"nameRaw": "[0x00019714]",
"unknown1": "[0x01]",
"facePictureIndex": 1,
"npcType": "Normal",
"npcTypeRaw": "65535 [0xFFFF]",
"faction": "Lord_Castellian",
"factionRaw": "395 [0x018B]",
"textRecordId1": 1050,
"textRecordId2": 0,
"index": 1,
"null1": 0
},
" 2: n_eadwyre:  (type? Permanent) (faction King_Eadwyre)": {
"variable": "n_eadwyre",
"nameRaw": "[0x00003285]",
"unknown1": "[0x01]",
"facePictureIndex": 80,
"npcType": "Permanent",
"npcTypeRaw": "65528 [0xFFF8]",
"faction": "King_Eadwyre",
"factionRaw": "390 [0x0186]",
"textRecordId1": 0,
"textRecordId2": 0,
"index": 2,
"null1": 0
}
}
,"locations: [1]": {
" 0: l_castfort: OutOfTown House1": {
"variable": "l_castfort",
"nameRaw": "[0x000065a4]",
"generalLocation": "OutOfTown",
"locationType": 17,
"LocationType": "House1",
"fineLocation": 0,
"knownLocation": "None",
"doorSelector": 0,
"textRecordId1": 0,
"textRecordId2": 0,
"index": 0,
"flags": "0 [0x00]",
"objPtr": 0,
"unknown1": "0 [0x0000]"
}
}
,"timers: [3]": {
" 0: t_0: Fixed 1.00:00:00": {
"variable": "t_0",
"nameRaw": "[0x40000000]",
"type": "Fixed",
"typeRaw": "1 [0x01]",
"minimum": "1.00:00:00",
"maximum": "00:00:00",
"flags1": "1 [00000001]",
"flags2": "0 [00]",
"duration": 0,
"started": 0,
"index": 0
},
" 1: t_1stparton: 1.5 times travel time between here and 'l_castfort'": {
"variable": "t_1stparton",
"nameRaw": "[0x0000a23c]",
"type": "Relative1",
"typeRaw": "2 [0x02]",
"minimum": "00:00:00",
"maximum": "00:00:00",
"flags1": "17 [00010001]",
"flags2": "0 [00]",
"duration": 0,
"started": 0,
"index": 1
},
" 2: t_15: Random between 3.00:00:00 and 7.00:00:00": {
"variable": "t_15",
"nameRaw": "[0x4000000f]",
"type": "Random",
"typeRaw": "0 [0x00]",
"minimum": "3.00:00:00",
"maximum": "7.00:00:00",
"flags1": "1 [00000001]",
"flags2": "0 [00]",
"duration": 0,
"started": 0,
"index": 2
}
}
,"mobs: [2]": {
" 0: m_0: 1 Knight": {
"variable": "m_0",
"nameRaw": "[0X44000000]",
"type": "Knight",
"count": 1,
"null1": 0,
"null2": 0,
"index": 0
},
" 1: m_battlemage: 1 Battlemage": {
"variable": "m_battlemage",
"nameRaw": "[0X000195ef]",
"type": "Battlemage",
"count": 1,
"null1": 0,
"null2": 0,
"index": 1
}
}
,"opCodes: [72]": {
" 0:  => StartTimer (t_0); When it expires: set s_0": {
"opCode": 12,
"argCount": 2,
"arguments:": {
"0: _": {
"type": "State",
"value": "-1",
"not": "False",
"index": "255",
"unknown1": "0 [0x00000000]"
},
"1: t_0": {
"type": "Timer",
"value": "0",
"not": "False",
"index": "0",
"unknown1": "0 [0x00000000]"
}
},
"messageId": -1,
"flags": "0 [0x0000]",
"lastUpdate": 0
},
" 1:  => CreateLogEntry (1019, 0)": {
"opCode": 23,
"argCount": 3,
"arguments:": {
"0: _": {
"type": "State",
"value": "-1",
"not": "False",
"index": "255",
"unknown1": "0 [0x00000000]"
},
"1: 1019": {
"type": "Value",
"value": "1019",
"not": "False",
"index": "0",
"unknown1": "0 [0x00000000]"
},
"2: 0": {
"type": "Value",
"value": "0",
"not": "False",
"index": "0",
"unknown1": "0 [0x00000000]"
}
},
"messageId": -1,
"flags": "0 [0x0000]",
"lastUpdate": 0
},
" 2:  => PickOneOf (s_13, s_24)": {
"opCode": 34,
"argCount": 5,
"arguments:": {
"0: _": {
"type": "State",
"value": "-1",
"not": "False",
"index": "255",
"unknown1": "0 [0x00000000]"
},
"1: s_13": {
"type": "State",
"value": "13",
"not": "False",
"index": "13",
"unknown1": "0 [0x00000000]"
},
"2: s_24": {
"type": "State",
"value": "24",
"not": "False",
"index": "24",
"unknown1": "0 [0x00000000]"
},
"3: ": {
"type": "State",
"value": "-2",
"not": "False",
"index": "254",
"unknown1": "0 [0x00000000]"
},
"4: ": {
"type": "State",
"value": "-2",
"not": "False",
"index": "254",
"unknown1": "0 [0x00000000]"
}
},
"messageId": -1,
"flags": "0 [0x0000]",
"lastUpdate": 0
},
" 3:  => PromptYesNo (s_yes, s_no, 1000)": {
"opCode": 29,
"argCount": 4,
"arguments:": {
"0: _": {
"type": "State",
"value": "-1",
"not": "False",
"index": "255",
"unknown1": "0 [0x00000000]"
},
"1: s_yes": {
"type": "State",
"value": "10",
"not": "False",
"index": "10",
"unknown1": "0 [0x00000000]"
},
"2: s_no": {
"type": "State",
"value": "11",
"not": "False",
"index": "11",
"unknown1": "0 [0x00000000]"
},
"3: 1000": {
"type": "Value",
"value": "1000",
"not": "False",
"index": "0",
"unknown1": "0 [0x00000000]"
}
},
"messageId": -1,
"flags": "0 [0x0000]",
"lastUpdate": 0
},
" 4: s_0 => EnsureNpcLocation (l_castfort)": {
"opCode": 81,
"argCount": 3,
"arguments:": {
"0: s_0": {
"type": "State",
"value": "0",
"not": "False",
"index": "0",
"unknown1": "0 [0x00000000]"
},
"1: l_castfort": {
"type": "Location",
"value": "0",
"not": "False",
"index": "0",
"unknown1": "0 [0x00000000]"
},
"2: ": {
"type": "Npc",
"value": "-1",
"not": "False",
"index": "255",
"unknown1": "0 [0x00000000]"
}
},
"messageId": -1,
"flags": "0 [0x0000]",
"lastUpdate": 0
},
" 5: s_0 => PlaceNpcAt (n_01, l_castfort)": {
"opCode": 30,
"argCount": 3,
"arguments:": {
"0: s_0": {
"type": "State",
"value": "0",
"not": "False",
"index": "0",
"unknown1": "0 [0x00000000]"
},
"1: n_01": {
"type": "Npc",
"value": "1",
"not": "False",
"index": "1",
"unknown1": "0 [0x00000000]"
},
"2: l_castfort": {
"type": "Location",
"value": "0",
"not": "False",
"index": "0",
"unknown1": "0 [0x00000000]"
}
},
"messageId": -1,
"flags": "0 [0x0000]",
"lastUpdate": 0
},
" 6:  >> IfNpcClicked (n_00): set s_1": {
"opCode": 28,
"argCount": 2,
"arguments:": {
"0: s_1": {
"type": "State",
"value": "1",
"not": "False",
"index": "1",
"unknown1": "0 [0x00000000]"
},
"1: n_00": {
"type": "Npc",
"value": "0",
"not": "False",
"index": "0",
"unknown1": "0 [0x00000000]"
}
},
"messageId": -1,
"flags": "0 [0x0000]",
"lastUpdate": 0
},
" 7:  >> IfGivingItemToNpc (i_03, n_01): set s_2": {
"opCode": 1,
"argCount": 3,
"arguments:": {
"0: s_2": {
"type": "State",
"value": "2",
"not": "False",
"index": "2",
"unknown1": "0 [0x00000000]"
},
"1: i_03": {
"type": "Item",
"value": "3",
"not": "False",
"index": "3",
"unknown1": "0 [0x00000000]"
},
"2: n_01": {
"type": "Npc",
"value": "1",
"not": "False",
"index": "1",
"unknown1": "0 [0x00000000]"
}
},
"messageId": -1,
"flags": "0 [0x0000]",
"lastUpdate": 0
},
" 8:  >> IfGivingItemToNpc (i_00, n_01): set s_2": {
"opCode": 1,
"argCount": 3,
"arguments:": {
"0: s_2": {
"type": "State",
"value": "2",
"not": "False",
"index": "2",
"unknown1": "0 [0x00000000]"
},
"1: i_00": {
"type": "Item",
"value": "0",
"not": "False",
"index": "0",
"unknown1": "0 [0x00000000]"
},
"2: n_01": {
"type": "Npc",
"value": "1",
"not": "False",
"index": "1",
"unknown1": "0 [0x00000000]"
}
},
"messageId": -1,
"flags": "0 [0x0000]",
"lastUpdate": 0
},
" 9:  >> If (s_1 and s_0): set s_3": {
"opCode": 52,
"argCount": 5,
"arguments:": {
"0: s_3": {
"type": "State",
"value": "3",
"not": "False",
"index": "3",
"unknown1": "0 [0x00000000]"
},
"1: s_1": {
"type": "State",
"value": "1",
"not": "False",
"index": "1",
"unknown1": "0 [0x00000000]"
},
"2: s_0": {
"type": "State",
"value": "0",
"not": "False",
"index": "0",
"unknown1": "0 [0x00000000]"
},
"3: ": {
"type": "State",
"value": "-2",
"not": "False",
"index": "254",
"unknown1": "0 [0x00000000]"
},
"4: ": {
"type": "State",
"value": "-2",
"not": "False",
"index": "254",
"unknown1": "0 [0x00000000]"
}
},
"messageId": -1,
"flags": "0 [0x0000]",
"lastUpdate": 0
},
"10: s_3 => StartTimer (t_1stparton); When it expires: set s_1stparton": {
"opCode": 12,
"argCount": 2,
"arguments:": {
"0: s_3": {
"type": "State",
"value": "3",
"not": "False",
"index": "3",
"unknown1": "0 [0x00000000]"
},
"1: t_1stparton": {
"type": "Timer",
"value": "1",
"not": "False",
"index": "1",
"unknown1": "0 [0x00000000]"
}
},
"messageId": -1,
"flags": "0 [0x0000]",
"lastUpdate": 0
},
"11: s_3 => CreateLogEntry (1020, 1)": {
"opCode": 23,
"argCount": 3,
"arguments:": {
"0: s_3": {
"type": "State",
"value": "3",
"not": "False",
"index": "3",
"unknown1": "0 [0x00000000]"
},
"1: 1020": {
"type": "Value",
"value": "1020",
"not": "False",
"index": "0",
"unknown1": "0 [0x00000000]"
},
"2: 1": {
"type": "Value",
"value": "1",
"not": "False",
"index": "0",
"unknown1": "0 [0x00000000]"
}
},
"messageId": -1,
"flags": "0 [0x0000]",
"lastUpdate": 0
},
"12: s_3 => RemoveLogFromSlot (0)": {
"opCode": 24,
"argCount": 2,
"arguments:": {
"0: s_3": {
"type": "State",
"value": "3",
"not": "False",
"index": "3",
"unknown1": "0 [0x00000000]"
},
"1: 0": {
"type": "Value",
"value": "0",
"not": "False",
"index": "0",
"unknown1": "0 [0x00000000]"
}
},
"messageId": -1,
"flags": "0 [0x0000]",
"lastUpdate": 0
},
"13: s_3 => Say (1027)": {
"opCode": 51,
"argCount": 1,
"arguments:": {
"0: s_3": {
"type": "State",
"value": "3",
"not": "False",
"index": "3",
"unknown1": "0 [0x00000000]"
}
},
"messageId": 1027,
"flags": "0 [0x0000]",
"lastUpdate": 0
},
"14: s_3 => AddTopics (n_01)": {
"opCode": 10,
"argCount": 4,
"arguments:": {
"0: s_3": {
"type": "State",
"value": "3",
"not": "False",
"index": "3",
"unknown1": "0 [0x00000000]"
},
"1: ": {
"type": "Location",
"value": "-1",
"not": "False",
"index": "255",
"unknown1": "0 [0x00000000]"
},
"2: n_01": {
"type": "Npc",
"value": "1",
"not": "False",
"index": "1",
"unknown1": "0 [0x00000000]"
},
"3: ": {
"type": "Item",
"value": "-1",
"not": "False",
"index": "255",
"unknown1": "0 [0x00000000]"
}
},
"messageId": -1,
"flags": "0 [0x0000]",
"lastUpdate": 0
},
"15:  >> IfGivingItemToNpc (i_02, n_00): set s_4": {
"opCode": 1,
"argCount": 3,
"arguments:": {
"0: s_4": {
"type": "State",
"value": "4",
"not": "False",
"index": "4",
"unknown1": "0 [0x00000000]"
},
"1: i_02": {
"type": "Item",
"value": "2",
"not": "False",
"index": "2",
"unknown1": "0 [0x00000000]"
},
"2: n_00": {
"type": "Npc",
"value": "0",
"not": "False",
"index": "0",
"unknown1": "0 [0x00000000]"
}
},
"messageId": -1,
"flags": "0 [0x0000]",
"lastUpdate": 0
},
"16: s_4 => QuestSuccess (i_magicitem)": {
"opCode": 4,
"argCount": 5,
"arguments:": {
"0: s_4": {
"type": "State",
"value": "4",
"not": "False",
"index": "4",
"unknown1": "0 [0x00000000]"
},
"1: i_magicitem": {
"type": "Item",
"value": "1",
"not": "False",
"index": "1",
"unknown1": "0 [0x00000000]"
},
"2: ": {
"type": "Item",
"value": "-1",
"not": "False",
"index": "255",
"unknown1": "0 [0x00000000]"
},
"3: ": {
"type": "Item",
"value": "-1",
"not": "False",
"index": "255",
"unknown1": "0 [0x00000000]"
},
"4: ": {
"type": "Item",
"value": "-1",
"not": "False",
"index": "255",
"unknown1": "0 [0x00000000]"
}
},
"messageId": -1,
"flags": "0 [0x0000]",
"lastUpdate": 0
},
"17: s_4 => AdjustReputationWithNpc (n_00, 10)": {
"opCode": 61,
"argCount": 3,
"arguments:": {
"0: s_4": {
"type": "State",
"value": "4",
"not": "False",
"index": "4",
"unknown1": "0 [0x00000000]"
},
"1: n_00": {
"type": "Npc",
"value": "0",
"not": "False",
"index": "0",
"unknown1": "0 [0x00000000]"
},
"2: 10": {
"type": "Value",
"value": "10",
"not": "False",
"index": "0",
"unknown1": "0 [0x00000000]"
}
},
"messageId": -1,
"flags": "0 [0x0000]",
"lastUpdate": 0
},
"18: s_4 => UnsetQuestor (n_eadwyre)": {
"opCode": 86,
"argCount": 2,
"arguments:": {
"0: s_4": {
"type": "State",
"value": "4",
"not": "False",
"index": "4",
"unknown1": "0 [0x00000000]"
},
"1: n_eadwyre": {
"type": "Npc",
"value": "2",
"not": "False",
"index": "2",
"unknown1": "0 [0x00000000]"
}
},
"messageId": -1,
"flags": "0 [0x0000]",
"lastUpdate": 0
},
"19: s_4 => UnsetQuestor (n_00)": {
"opCode": 86,
"argCount": 2,
"arguments:": {
"0: s_4": {
"type": "State",
"value": "4",
"not": "False",
"index": "4",
"unknown1": "0 [0x00000000]"
},
"1: n_00": {
"type": "Npc",
"value": "0",
"not": "False",
"index": "0",
"unknown1": "0 [0x00000000]"
}
},
"messageId": -1,
"flags": "0 [0x0000]",
"lastUpdate": 0
},
"20:  >> IfGivingItemToNpc (i_03, n_eadwyre): set s_5": {
"opCode": 1,
"argCount": 3,
"arguments:": {
"0: s_5": {
"type": "State",
"value": "5",
"not": "False",
"index": "5",
"unknown1": "0 [0x00000000]"
},
"1: i_03": {
"type": "Item",
"value": "3",
"not": "False",
"index": "3",
"unknown1": "0 [0x00000000]"
},
"2: n_eadwyre": {
"type": "Npc",
"value": "2",
"not": "False",
"index": "2",
"unknown1": "0 [0x00000000]"
}
},
"messageId": -1,
"flags": "0 [0x0000]",
"lastUpdate": 0
},
"21:  >> IfGivingItemToNpc (i_00, n_eadwyre): set s_5": {
"opCode": 1,
"argCount": 3,
"arguments:": {
"0: s_5": {
"type": "State",
"value": "5",
"not": "False",
"index": "5",
"unknown1": "0 [0x00000000]"
},
"1: i_00": {
"type": "Item",
"value": "0",
"not": "False",
"index": "0",
"unknown1": "0 [0x00000000]"
},
"2: n_eadwyre": {
"type": "Npc",
"value": "2",
"not": "False",
"index": "2",
"unknown1": "0 [0x00000000]"
}
},
"messageId": -1,
"flags": "0 [0x0000]",
"lastUpdate": 0
},
"22: s_5 => Say (1014)": {
"opCode": 51,
"argCount": 1,
"arguments:": {
"0: s_5": {
"type": "State",
"value": "5",
"not": "False",
"index": "5",
"unknown1": "0 [0x00000000]"
}
},
"messageId": 1014,
"flags": "0 [0x0000]",
"lastUpdate": 0
},
"23: s_5 => AdjustReputationWithNpc (n_eadwyre, 5)": {
"opCode": 61,
"argCount": 3,
"arguments:": {
"0: s_5": {
"type": "State",
"value": "5",
"not": "False",
"index": "5",
"unknown1": "0 [0x00000000]"
},
"1: n_eadwyre": {
"type": "Npc",
"value": "2",
"not": "False",
"index": "2",
"unknown1": "0 [0x00000000]"
},
"2: 5": {
"type": "Value",
"value": "5",
"not": "False",
"index": "0",
"unknown1": "0 [0x00000000]"
}
},
"messageId": -1,
"flags": "0 [0x0000]",
"lastUpdate": 0
},
"24: gs_ElysannaSatisfied => StartTimer (t_15); When it expires: set s_15": {
"opCode": 12,
"argCount": 2,
"arguments:": {
"0: gs_ElysannaSatisfied": {
"type": "State",
"value": "6",
"not": "False",
"index": "6",
"unknown1": "0 [0x00000000]"
},
"1: t_15": {
"type": "Timer",
"value": "2",
"not": "False",
"index": "2",
"unknown1": "0 [0x00000000]"
}
},
"messageId": -1,
"flags": "0 [0x0000]",
"lastUpdate": 0
},
"25:  >> IfMobHurtByPlayer (m_0): set s_8 [Msg 1025]": {
"opCode": 21,
"argCount": 2,
"arguments:": {
"0: s_8": {
"type": "State",
"value": "8",
"not": "False",
"index": "8",
"unknown1": "0 [0x00000000]"
},
"1: m_0": {
"type": "Mob",
"value": "0",
"not": "False",
"index": "0",
"unknown1": "0 [0x00000000]"
}
},
"messageId": 1025,
"flags": "0 [0x0000]",
"lastUpdate": 0
},
"26:  >> IfMobHurtByPlayer (m_battlemage): set s_8 [Msg 1025]": {
"opCode": 21,
"argCount": 2,
"arguments:": {
"0: s_8": {
"type": "State",
"value": "8",
"not": "False",
"index": "8",
"unknown1": "0 [0x00000000]"
},
"1: m_battlemage": {
"type": "Mob",
"value": "1",
"not": "False",
"index": "1",
"unknown1": "0 [0x00000000]"
}
},
"messageId": 1025,
"flags": "0 [0x0000]",
"lastUpdate": 0
},
"27:  >> If (s_1 and not s_3): set s_clearclick": {
"opCode": 52,
"argCount": 5,
"arguments:": {
"0: s_clearclick": {
"type": "State",
"value": "9",
"not": "False",
"index": "9",
"unknown1": "0 [0x00000000]"
},
"1: s_1": {
"type": "State",
"value": "1",
"not": "False",
"index": "1",
"unknown1": "0 [0x00000000]"
},
"2: not s_3": {
"type": "State",
"value": "3",
"not": "True",
"index": "3",
"unknown1": "0 [0x00000000]"
},
"3: ": {
"type": "State",
"value": "-2",
"not": "False",
"index": "254",
"unknown1": "0 [0x00000000]"
},
"4: ": {
"type": "State",
"value": "-2",
"not": "False",
"index": "254",
"unknown1": "0 [0x00000000]"
}
},
"messageId": -1,
"flags": "0 [0x0000]",
"lastUpdate": 0
},
"28: s_clearclick => Unset (s_1, s_clearclick)": {
"opCode": 7,
"argCount": 5,
"arguments:": {
"0: s_clearclick": {
"type": "State",
"value": "9",
"not": "False",
"index": "9",
"unknown1": "0 [0x00000000]"
},
"1: s_1": {
"type": "State",
"value": "1",
"not": "False",
"index": "1",
"unknown1": "0 [0x00000000]"
},
"2: s_clearclick": {
"type": "State",
"value": "9",
"not": "False",
"index": "9",
"unknown1": "0 [0x00000000]"
},
"3: ": {
"type": "State",
"value": "-2",
"not": "False",
"index": "254",
"unknown1": "0 [0x00000000]"
},
"4: ": {
"type": "State",
"value": "-2",
"not": "False",
"index": "254",
"unknown1": "0 [0x00000000]"
}
},
"messageId": -1,
"flags": "0 [0x0000]",
"lastUpdate": 0
},
"29: s_yes => Say (1002)": {
"opCode": 51,
"argCount": 1,
"arguments:": {
"0: s_yes": {
"type": "State",
"value": "10",
"not": "False",
"index": "10",
"unknown1": "0 [0x00000000]"
}
},
"messageId": 1002,
"flags": "0 [0x0000]",
"lastUpdate": 0
},
"30: s_yes => SetQuestor (n_00)": {
"opCode": 85,
"argCount": 2,
"arguments:": {
"0: s_yes": {
"type": "State",
"value": "10",
"not": "False",
"index": "10",
"unknown1": "0 [0x00000000]"
},
"1: n_00": {
"type": "Npc",
"value": "0",
"not": "False",
"index": "0",
"unknown1": "0 [0x00000000]"
}
},
"messageId": -1,
"flags": "0 [0x0000]",
"lastUpdate": 0
},
"31: s_yes => SetQuestor (n_eadwyre)": {
"opCode": 85,
"argCount": 2,
"arguments:": {
"0: s_yes": {
"type": "State",
"value": "10",
"not": "False",
"index": "10",
"unknown1": "0 [0x00000000]"
},
"1: n_eadwyre": {
"type": "Npc",
"value": "2",
"not": "False",
"index": "2",
"unknown1": "0 [0x00000000]"
}
},
"messageId": -1,
"flags": "0 [0x0000]",
"lastUpdate": 0
},
"32: s_yes => RemoveTopics (n_01)": {
"opCode": 11,
"argCount": 4,
"arguments:": {
"0: s_yes": {
"type": "State",
"value": "10",
"not": "False",
"index": "10",
"unknown1": "0 [0x00000000]"
},
"1: ": {
"type": "Location",
"value": "-1",
"not": "False",
"index": "255",
"unknown1": "0 [0x00000000]"
},
"2: n_01": {
"type": "Npc",
"value": "1",
"not": "False",
"index": "1",
"unknown1": "0 [0x00000000]"
},
"3: ": {
"type": "Item",
"value": "-1",
"not": "False",
"index": "255",
"unknown1": "0 [0x00000000]"
}
},
"messageId": -1,
"flags": "0 [0x0000]",
"lastUpdate": 0
},
"33: s_no => Say (1001)": {
"opCode": 51,
"argCount": 1,
"arguments:": {
"0: s_no": {
"type": "State",
"value": "11",
"not": "False",
"index": "11",
"unknown1": "0 [0x00000000]"
}
},
"messageId": 1001,
"flags": "0 [0x0000]",
"lastUpdate": 0
},
"34: s_no => EndQuest ()": {
"opCode": 6,
"argCount": 1,
"arguments:": {
"0: s_no": {
"type": "State",
"value": "11",
"not": "False",
"index": "11",
"unknown1": "0 [0x00000000]"
}
},
"messageId": -1,
"flags": "0 [0x0000]",
"lastUpdate": 0
},
"35:  >> If (s_3 and s_13): set s_12": {
"opCode": 52,
"argCount": 5,
"arguments:": {
"0: s_12": {
"type": "State",
"value": "12",
"not": "False",
"index": "12",
"unknown1": "0 [0x00000000]"
},
"1: s_3": {
"type": "State",
"value": "3",
"not": "False",
"index": "3",
"unknown1": "0 [0x00000000]"
},
"2: s_13": {
"type": "State",
"value": "13",
"not": "False",
"index": "13",
"unknown1": "0 [0x00000000]"
},
"3: ": {
"type": "State",
"value": "-2",
"not": "False",
"index": "254",
"unknown1": "0 [0x00000000]"
},
"4: ": {
"type": "State",
"value": "-2",
"not": "False",
"index": "254",
"unknown1": "0 [0x00000000]"
}
},
"messageId": -1,
"flags": "0 [0x0000]",
"lastUpdate": 0
},
"36: s_12 => PlaceItemOnCharacter (i_00)": {
"opCode": 26,
"argCount": 3,
"arguments:": {
"0: s_12": {
"type": "State",
"value": "12",
"not": "False",
"index": "12",
"unknown1": "0 [0x00000000]"
},
"1: i_00": {
"type": "Item",
"value": "0",
"not": "False",
"index": "0",
"unknown1": "0 [0x00000000]"
},
"2: ": {
"type": "Npc",
"value": "-1",
"not": "False",
"index": "255",
"unknown1": "0 [0x00000000]"
}
},
"messageId": -1,
"flags": "0 [0x0000]",
"lastUpdate": 0
},
"37: s_12 >> WhenItemIsUsed (i_00): set s_7": {
"opCode": 57,
"argCount": 3,
"arguments:": {
"0: s_12": {
"type": "State",
"value": "12",
"not": "False",
"index": "12",
"unknown1": "0 [0x00000000]"
},
"1: s_7": {
"type": "State",
"value": "7",
"not": "False",
"index": "7",
"unknown1": "0 [0x00000000]"
},
"2: i_00": {
"type": "Item",
"value": "0",
"not": "False",
"index": "0",
"unknown1": "0 [0x00000000]"
}
},
"messageId": -1,
"flags": "0 [0x0000]",
"lastUpdate": 0
},
"38:  >> If (s_3 and s_24): set s_14": {
"opCode": 52,
"argCount": 5,
"arguments:": {
"0: s_14": {
"type": "State",
"value": "14",
"not": "False",
"index": "14",
"unknown1": "0 [0x00000000]"
},
"1: s_3": {
"type": "State",
"value": "3",
"not": "False",
"index": "3",
"unknown1": "0 [0x00000000]"
},
"2: s_24": {
"type": "State",
"value": "24",
"not": "False",
"index": "24",
"unknown1": "0 [0x00000000]"
},
"3: ": {
"type": "State",
"value": "-2",
"not": "False",
"index": "254",
"unknown1": "0 [0x00000000]"
},
"4: ": {
"type": "State",
"value": "-2",
"not": "False",
"index": "254",
"unknown1": "0 [0x00000000]"
}
},
"messageId": -1,
"flags": "0 [0x0000]",
"lastUpdate": 0
},
"39: s_14 => PlaceItemOnCharacter (i_03)": {
"opCode": 26,
"argCount": 3,
"arguments:": {
"0: s_14": {
"type": "State",
"value": "14",
"not": "False",
"index": "14",
"unknown1": "0 [0x00000000]"
},
"1: i_03": {
"type": "Item",
"value": "3",
"not": "False",
"index": "3",
"unknown1": "0 [0x00000000]"
},
"2: ": {
"type": "Npc",
"value": "-1",
"not": "False",
"index": "255",
"unknown1": "0 [0x00000000]"
}
},
"messageId": -1,
"flags": "0 [0x0000]",
"lastUpdate": 0
},
"40: s_14 >> WhenItemIsUsed (i_03): set s_7": {
"opCode": 57,
"argCount": 3,
"arguments:": {
"0: s_14": {
"type": "State",
"value": "14",
"not": "False",
"index": "14",
"unknown1": "0 [0x00000000]"
},
"1: s_7": {
"type": "State",
"value": "7",
"not": "False",
"index": "7",
"unknown1": "0 [0x00000000]"
},
"2: i_03": {
"type": "Item",
"value": "3",
"not": "False",
"index": "3",
"unknown1": "0 [0x00000000]"
}
},
"messageId": -1,
"flags": "0 [0x0000]",
"lastUpdate": 0
},
"41: s_15 => PlaceItemOnCharacter (i_04)": {
"opCode": 26,
"argCount": 3,
"arguments:": {
"0: s_15": {
"type": "State",
"value": "15",
"not": "False",
"index": "15",
"unknown1": "0 [0x00000000]"
},
"1: i_04": {
"type": "Item",
"value": "4",
"not": "False",
"index": "4",
"unknown1": "0 [0x00000000]"
},
"2: ": {
"type": "Npc",
"value": "-1",
"not": "False",
"index": "255",
"unknown1": "0 [0x00000000]"
}
},
"messageId": -1,
"flags": "0 [0x0000]",
"lastUpdate": 0
},
"42: s_15 => PlaceItemOnCharacter (i_6)": {
"opCode": 26,
"argCount": 3,
"arguments:": {
"0: s_15": {
"type": "State",
"value": "15",
"not": "False",
"index": "15",
"unknown1": "0 [0x00000000]"
},
"1: i_6": {
"type": "Item",
"value": "5",
"not": "False",
"index": "5",
"unknown1": "0 [0x00000000]"
},
"2: ": {
"type": "Npc",
"value": "-1",
"not": "False",
"index": "255",
"unknown1": "0 [0x00000000]"
}
},
"messageId": -1,
"flags": "0 [0x0000]",
"lastUpdate": 0
},
"43: s_15 => MakePermanent (i_04)": {
"opCode": 54,
"argCount": 2,
"arguments:": {
"0: s_15": {
"type": "State",
"value": "15",
"not": "False",
"index": "15",
"unknown1": "0 [0x00000000]"
},
"1: i_04": {
"type": "Item",
"value": "4",
"not": "False",
"index": "4",
"unknown1": "0 [0x00000000]"
}
},
"messageId": -1,
"flags": "0 [0x0000]",
"lastUpdate": 0
},
"44: s_15 => MakePermanent (i_6)": {
"opCode": 54,
"argCount": 2,
"arguments:": {
"0: s_15": {
"type": "State",
"value": "15",
"not": "False",
"index": "15",
"unknown1": "0 [0x00000000]"
},
"1: i_6": {
"type": "Item",
"value": "5",
"not": "False",
"index": "5",
"unknown1": "0 [0x00000000]"
}
},
"messageId": -1,
"flags": "0 [0x0000]",
"lastUpdate": 0
},
"45: s_15 => Say (1018)": {
"opCode": 51,
"argCount": 1,
"arguments:": {
"0: s_15": {
"type": "State",
"value": "15",
"not": "False",
"index": "15",
"unknown1": "0 [0x00000000]"
}
},
"messageId": 1018,
"flags": "0 [0x0000]",
"lastUpdate": 0
},
"46: s_15 => UnsetQuestor (n_eadwyre)": {
"opCode": 86,
"argCount": 2,
"arguments:": {
"0: s_15": {
"type": "State",
"value": "15",
"not": "False",
"index": "15",
"unknown1": "0 [0x00000000]"
},
"1: n_eadwyre": {
"type": "Npc",
"value": "2",
"not": "False",
"index": "2",
"unknown1": "0 [0x00000000]"
}
},
"messageId": -1,
"flags": "0 [0x0000]",
"lastUpdate": 0
},
"47: s_15 => UnsetQuestor (n_00)": {
"opCode": 86,
"argCount": 2,
"arguments:": {
"0: s_15": {
"type": "State",
"value": "15",
"not": "False",
"index": "15",
"unknown1": "0 [0x00000000]"
},
"1: n_00": {
"type": "Npc",
"value": "0",
"not": "False",
"index": "0",
"unknown1": "0 [0x00000000]"
}
},
"messageId": -1,
"flags": "0 [0x0000]",
"lastUpdate": 0
},
"48: s_15 => EndQuest ()": {
"opCode": 6,
"argCount": 1,
"arguments:": {
"0: s_15": {
"type": "State",
"value": "15",
"not": "False",
"index": "15",
"unknown1": "0 [0x00000000]"
}
},
"messageId": -1,
"flags": "0 [0x0000]",
"lastUpdate": 0
},
"49: s_1stparton => UnsetQuestor (n_eadwyre)": {
"opCode": 86,
"argCount": 2,
"arguments:": {
"0: s_1stparton": {
"type": "State",
"value": "16",
"not": "False",
"index": "16",
"unknown1": "0 [0x00000000]"
},
"1: n_eadwyre": {
"type": "Npc",
"value": "2",
"not": "False",
"index": "2",
"unknown1": "0 [0x00000000]"
}
},
"messageId": -1,
"flags": "0 [0x0000]",
"lastUpdate": 0
},
"50: s_1stparton => UnsetQuestor (n_00)": {
"opCode": 86,
"argCount": 2,
"arguments:": {
"0: s_1stparton": {
"type": "State",
"value": "16",
"not": "False",
"index": "16",
"unknown1": "0 [0x00000000]"
},
"1: n_00": {
"type": "Npc",
"value": "0",
"not": "False",
"index": "0",
"unknown1": "0 [0x00000000]"
}
},
"messageId": -1,
"flags": "0 [0x0000]",
"lastUpdate": 0
},
"51: s_1stparton => EndQuest ()": {
"opCode": 6,
"argCount": 1,
"arguments:": {
"0: s_1stparton": {
"type": "State",
"value": "16",
"not": "False",
"index": "16",
"unknown1": "0 [0x00000000]"
}
},
"messageId": -1,
"flags": "0 [0x0000]",
"lastUpdate": 0
},
"52:  >> If (s_4 and gs_ElysannaSatisfied): set s_17": {
"opCode": 52,
"argCount": 5,
"arguments:": {
"0: s_17": {
"type": "State",
"value": "17",
"not": "False",
"index": "17",
"unknown1": "0 [0x00000000]"
},
"1: s_4": {
"type": "State",
"value": "4",
"not": "False",
"index": "4",
"unknown1": "0 [0x00000000]"
},
"2: gs_ElysannaSatisfied": {
"type": "State",
"value": "6",
"not": "False",
"index": "6",
"unknown1": "0 [0x00000000]"
},
"3: ": {
"type": "State",
"value": "-2",
"not": "False",
"index": "254",
"unknown1": "0 [0x00000000]"
},
"4: ": {
"type": "State",
"value": "-2",
"not": "False",
"index": "254",
"unknown1": "0 [0x00000000]"
}
},
"messageId": -1,
"flags": "0 [0x0000]",
"lastUpdate": 0
},
"53: s_17 => Say (1012)": {
"opCode": 51,
"argCount": 1,
"arguments:": {
"0: s_17": {
"type": "State",
"value": "17",
"not": "False",
"index": "17",
"unknown1": "0 [0x00000000]"
}
},
"messageId": 1012,
"flags": "0 [0x0000]",
"lastUpdate": 0
},
"54:  >> If (s_4 and not gs_ElysannaSatisfied): set s_18": {
"opCode": 52,
"argCount": 5,
"arguments:": {
"0: s_18": {
"type": "State",
"value": "18",
"not": "False",
"index": "18",
"unknown1": "0 [0x00000000]"
},
"1: s_4": {
"type": "State",
"value": "4",
"not": "False",
"index": "4",
"unknown1": "0 [0x00000000]"
},
"2: not gs_ElysannaSatisfied": {
"type": "State",
"value": "6",
"not": "True",
"index": "6",
"unknown1": "0 [0x00000000]"
},
"3: ": {
"type": "State",
"value": "-2",
"not": "False",
"index": "254",
"unknown1": "0 [0x00000000]"
},
"4: ": {
"type": "State",
"value": "-2",
"not": "False",
"index": "254",
"unknown1": "0 [0x00000000]"
}
},
"messageId": -1,
"flags": "0 [0x0000]",
"lastUpdate": 0
},
"55: s_18 => Say (1011)": {
"opCode": 51,
"argCount": 1,
"arguments:": {
"0: s_18": {
"type": "State",
"value": "18",
"not": "False",
"index": "18",
"unknown1": "0 [0x00000000]"
}
},
"messageId": 1011,
"flags": "0 [0x0000]",
"lastUpdate": 0
},
"56:  >> If (s_2 and s_7): set s_19": {
"opCode": 52,
"argCount": 5,
"arguments:": {
"0: s_19": {
"type": "State",
"value": "19",
"not": "False",
"index": "19",
"unknown1": "0 [0x00000000]"
},
"1: s_2": {
"type": "State",
"value": "2",
"not": "False",
"index": "2",
"unknown1": "0 [0x00000000]"
},
"2: s_7": {
"type": "State",
"value": "7",
"not": "False",
"index": "7",
"unknown1": "0 [0x00000000]"
},
"3: ": {
"type": "State",
"value": "-2",
"not": "False",
"index": "254",
"unknown1": "0 [0x00000000]"
},
"4: ": {
"type": "State",
"value": "-2",
"not": "False",
"index": "254",
"unknown1": "0 [0x00000000]"
}
},
"messageId": -1,
"flags": "0 [0x0000]",
"lastUpdate": 0
},
"57: s_19 => CreateFoe(m_0, 4, 100%, 6)": {
"opCode": 9,
"argCount": 5,
"arguments:": {
"0: s_19": {
"type": "State",
"value": "19",
"not": "False",
"index": "19",
"unknown1": "0 [0x00000000]"
},
"1: m_0": {
"type": "Mob",
"value": "0",
"not": "False",
"index": "0",
"unknown1": "0 [0x00000000]"
},
"2: 4": {
"type": "Value",
"value": "4",
"not": "False",
"index": "0",
"unknown1": "0 [0x00000000]"
},
"3: 100": {
"type": "Value",
"value": "100",
"not": "False",
"index": "0",
"unknown1": "0 [0x00000000]"
},
"4: 6": {
"type": "Value",
"value": "6",
"not": "False",
"index": "0",
"unknown1": "0 [0x00000000]"
}
},
"messageId": -1,
"flags": "0 [0x0000]",
"lastUpdate": 0
},
"58: s_19 => CreateFoe(m_battlemage, 7, 100%, 2)": {
"opCode": 9,
"argCount": 5,
"arguments:": {
"0: s_19": {
"type": "State",
"value": "19",
"not": "False",
"index": "19",
"unknown1": "0 [0x00000000]"
},
"1: m_battlemage": {
"type": "Mob",
"value": "1",
"not": "False",
"index": "1",
"unknown1": "0 [0x00000000]"
},
"2: 7": {
"type": "Value",
"value": "7",
"not": "False",
"index": "0",
"unknown1": "0 [0x00000000]"
},
"3: 100": {
"type": "Value",
"value": "100",
"not": "False",
"index": "0",
"unknown1": "0 [0x00000000]"
},
"4: 2": {
"type": "Value",
"value": "2",
"not": "False",
"index": "0",
"unknown1": "0 [0x00000000]"
}
},
"messageId": -1,
"flags": "0 [0x0000]",
"lastUpdate": 0
},
"59: s_19 => Say (1030)": {
"opCode": 51,
"argCount": 1,
"arguments:": {
"0: s_19": {
"type": "State",
"value": "19",
"not": "False",
"index": "19",
"unknown1": "0 [0x00000000]"
}
},
"messageId": 1030,
"flags": "0 [0x0000]",
"lastUpdate": 0
},
"60: s_19 => AdjustReputationWithNpc (n_01, -10)": {
"opCode": 61,
"argCount": 3,
"arguments:": {
"0: s_19": {
"type": "State",
"value": "19",
"not": "False",
"index": "19",
"unknown1": "0 [0x00000000]"
},
"1: n_01": {
"type": "Npc",
"value": "1",
"not": "False",
"index": "1",
"unknown1": "0 [0x00000000]"
},
"2: -10": {
"type": "Value",
"value": "-10",
"not": "False",
"index": "0",
"unknown1": "0 [0x00000000]"
}
},
"messageId": -1,
"flags": "0 [0x0000]",
"lastUpdate": 0
},
"61:  >> If (s_2 and not s_7): set s_20": {
"opCode": 52,
"argCount": 5,
"arguments:": {
"0: s_20": {
"type": "State",
"value": "20",
"not": "False",
"index": "20",
"unknown1": "0 [0x00000000]"
},
"1: s_2": {
"type": "State",
"value": "2",
"not": "False",
"index": "2",
"unknown1": "0 [0x00000000]"
},
"2: not s_7": {
"type": "State",
"value": "7",
"not": "True",
"index": "7",
"unknown1": "0 [0x00000000]"
},
"3: ": {
"type": "State",
"value": "-2",
"not": "False",
"index": "254",
"unknown1": "0 [0x00000000]"
},
"4: ": {
"type": "State",
"value": "-2",
"not": "False",
"index": "254",
"unknown1": "0 [0x00000000]"
}
},
"messageId": -1,
"flags": "0 [0x0000]",
"lastUpdate": 0
},
"62: s_20 => PlaceItemOnCharacter (i_02)": {
"opCode": 26,
"argCount": 3,
"arguments:": {
"0: s_20": {
"type": "State",
"value": "20",
"not": "False",
"index": "20",
"unknown1": "0 [0x00000000]"
},
"1: i_02": {
"type": "Item",
"value": "2",
"not": "False",
"index": "2",
"unknown1": "0 [0x00000000]"
},
"2: ": {
"type": "Npc",
"value": "-1",
"not": "False",
"index": "255",
"unknown1": "0 [0x00000000]"
}
},
"messageId": -1,
"flags": "0 [0x0000]",
"lastUpdate": 0
},
"63: s_20 >> WhenItemIsUsed (i_02): set s_21": {
"opCode": 57,
"argCount": 3,
"arguments:": {
"0: s_20": {
"type": "State",
"value": "20",
"not": "False",
"index": "20",
"unknown1": "0 [0x00000000]"
},
"1: s_21": {
"type": "State",
"value": "21",
"not": "False",
"index": "21",
"unknown1": "0 [0x00000000]"
},
"2: i_02": {
"type": "Item",
"value": "2",
"not": "False",
"index": "2",
"unknown1": "0 [0x00000000]"
}
},
"messageId": -1,
"flags": "0 [0x0000]",
"lastUpdate": 0
},
"64: s_20 => Say (1028)": {
"opCode": 51,
"argCount": 1,
"arguments:": {
"0: s_20": {
"type": "State",
"value": "20",
"not": "False",
"index": "20",
"unknown1": "0 [0x00000000]"
}
},
"messageId": 1028,
"flags": "0 [0x0000]",
"lastUpdate": 0
},
"65:  >> If (s_4 and s_21): set s_22": {
"opCode": 52,
"argCount": 5,
"arguments:": {
"0: s_22": {
"type": "State",
"value": "22",
"not": "False",
"index": "22",
"unknown1": "0 [0x00000000]"
},
"1: s_4": {
"type": "State",
"value": "4",
"not": "False",
"index": "4",
"unknown1": "0 [0x00000000]"
},
"2: s_21": {
"type": "State",
"value": "21",
"not": "False",
"index": "21",
"unknown1": "0 [0x00000000]"
},
"3: ": {
"type": "State",
"value": "-2",
"not": "False",
"index": "254",
"unknown1": "0 [0x00000000]"
},
"4: ": {
"type": "State",
"value": "-2",
"not": "False",
"index": "254",
"unknown1": "0 [0x00000000]"
}
},
"messageId": -1,
"flags": "0 [0x0000]",
"lastUpdate": 0
},
"66: s_22 => Say (1031)": {
"opCode": 51,
"argCount": 1,
"arguments:": {
"0: s_22": {
"type": "State",
"value": "22",
"not": "False",
"index": "22",
"unknown1": "0 [0x00000000]"
}
},
"messageId": 1031,
"flags": "0 [0x0000]",
"lastUpdate": 0
},
"67: s_22 => AdjustReputationWithNpc (n_00, -25)": {
"opCode": 61,
"argCount": 3,
"arguments:": {
"0: s_22": {
"type": "State",
"value": "22",
"not": "False",
"index": "22",
"unknown1": "0 [0x00000000]"
},
"1: n_00": {
"type": "Npc",
"value": "0",
"not": "False",
"index": "0",
"unknown1": "0 [0x00000000]"
},
"2: -25": {
"type": "Value",
"value": "-25",
"not": "False",
"index": "0",
"unknown1": "0 [0x00000000]"
}
},
"messageId": -1,
"flags": "0 [0x0000]",
"lastUpdate": 0
},
"68:  >> If (s_4 and not s_21): set s_23": {
"opCode": 52,
"argCount": 5,
"arguments:": {
"0: s_23": {
"type": "State",
"value": "23",
"not": "False",
"index": "23",
"unknown1": "0 [0x00000000]"
},
"1: s_4": {
"type": "State",
"value": "4",
"not": "False",
"index": "4",
"unknown1": "0 [0x00000000]"
},
"2: not s_21": {
"type": "State",
"value": "21",
"not": "True",
"index": "21",
"unknown1": "0 [0x00000000]"
},
"3: ": {
"type": "State",
"value": "-2",
"not": "False",
"index": "254",
"unknown1": "0 [0x00000000]"
},
"4: ": {
"type": "State",
"value": "-2",
"not": "False",
"index": "254",
"unknown1": "0 [0x00000000]"
}
},
"messageId": -1,
"flags": "0 [0x0000]",
"lastUpdate": 0
},
"69: s_23 >> StartQuest (S0000011)": {
"opCode": 8,
"argCount": 3,
"arguments:": {
"0: s_23": {
"type": "State",
"value": "23",
"not": "False",
"index": "23",
"unknown1": "0 [0x00000000]"
},
"1: 11": {
"type": "Value",
"value": "11",
"not": "False",
"index": "0",
"unknown1": "0 [0x00000000]"
},
"2: 11": {
"type": "Value",
"value": "11",
"not": "False",
"index": "0",
"unknown1": "0 [0x00000000]"
}
},
"messageId": -1,
"flags": "0 [0x0000]",
"lastUpdate": 0
},
"70:  >> If (s_22 or s_23): set s_25": {
"opCode": 53,
"argCount": 5,
"arguments:": {
"0: s_25": {
"type": "State",
"value": "25",
"not": "False",
"index": "25",
"unknown1": "0 [0x00000000]"
},
"1: s_22": {
"type": "State",
"value": "22",
"not": "False",
"index": "22",
"unknown1": "0 [0x00000000]"
},
"2: s_23": {
"type": "State",
"value": "23",
"not": "False",
"index": "23",
"unknown1": "0 [0x00000000]"
},
"3: ": {
"type": "State",
"value": "-2",
"not": "False",
"index": "254",
"unknown1": "0 [0x00000000]"
},
"4: ": {
"type": "State",
"value": "-2",
"not": "False",
"index": "254",
"unknown1": "0 [0x00000000]"
}
},
"messageId": -1,
"flags": "0 [0x0000]",
"lastUpdate": 0
},
"71: s_25 => EndQuest ()": {
"opCode": 6,
"argCount": 1,
"arguments:": {
"0: s_25": {
"type": "State",
"value": "25",
"not": "False",
"index": "25",
"unknown1": "0 [0x00000000]"
}
},
"messageId": -1,
"flags": "0 [0x0000]",
"lastUpdate": 0
}
}
,"states: [26]": {
" 0: s_0": {
"variable": "s_0",
"nameRaw": "[0x40000000]",
"isGlobal": false,
"globalIndex": 0,
"index": 0
},
" 1: s_1": {
"variable": "s_1",
"nameRaw": "[0x40000001]",
"isGlobal": false,
"globalIndex": 0,
"index": 1
},
" 2: s_2": {
"variable": "s_2",
"nameRaw": "[0x40000002]",
"isGlobal": false,
"globalIndex": 0,
"index": 2
},
" 3: s_3": {
"variable": "s_3",
"nameRaw": "[0x40000003]",
"isGlobal": false,
"globalIndex": 0,
"index": 3
},
" 4: s_4": {
"variable": "s_4",
"nameRaw": "[0x40000004]",
"isGlobal": false,
"globalIndex": 0,
"index": 4
},
" 5: s_5": {
"variable": "s_5",
"nameRaw": "[0x40000005]",
"isGlobal": false,
"globalIndex": 0,
"index": 5
},
" 6: gs_ElysannaSatisfied": {
"variable": "gs_ElysannaSatisfied",
"nameRaw": "[0x40000006]",
"isGlobal": true,
"globalIndex": 25,
"index": 6
},
" 7: s_7": {
"variable": "s_7",
"nameRaw": "[0x40000007]",
"isGlobal": false,
"globalIndex": 0,
"index": 7
},
" 8: s_8": {
"variable": "s_8",
"nameRaw": "[0x40000008]",
"isGlobal": false,
"globalIndex": 0,
"index": 8
},
" 9: s_clearclick": {
"variable": "s_clearclick",
"nameRaw": "[0x00019765]",
"isGlobal": false,
"globalIndex": 0,
"index": 9
},
"10: s_yes": {
"variable": "s_yes",
"nameRaw": "[0x00000321]",
"isGlobal": false,
"globalIndex": 0,
"index": 10
},
"11: s_no": {
"variable": "s_no",
"nameRaw": "[0x0000014b]",
"isGlobal": false,
"globalIndex": 0,
"index": 11
},
"12: s_12": {
"variable": "s_12",
"nameRaw": "[0x4000000c]",
"isGlobal": false,
"globalIndex": 0,
"index": 12
},
"13: s_13": {
"variable": "s_13",
"nameRaw": "[0x4000000d]",
"isGlobal": false,
"globalIndex": 0,
"index": 13
},
"14: s_14": {
"variable": "s_14",
"nameRaw": "[0x4000000e]",
"isGlobal": false,
"globalIndex": 0,
"index": 14
},
"15: s_15": {
"variable": "s_15",
"nameRaw": "[0x4000000f]",
"isGlobal": false,
"globalIndex": 0,
"index": 15
},
"16: s_1stparton": {
"variable": "s_1stparton",
"nameRaw": "[0x0000a23c]",
"isGlobal": false,
"globalIndex": 0,
"index": 16
},
"17: s_17": {
"variable": "s_17",
"nameRaw": "[0x40000011]",
"isGlobal": false,
"globalIndex": 0,
"index": 17
},
"18: s_18": {
"variable": "s_18",
"nameRaw": "[0x40000012]",
"isGlobal": false,
"globalIndex": 0,
"index": 18
},
"19: s_19": {
"variable": "s_19",
"nameRaw": "[0x40000013]",
"isGlobal": false,
"globalIndex": 0,
"index": 19
},
"20: s_20": {
"variable": "s_20",
"nameRaw": "[0x40000014]",
"isGlobal": false,
"globalIndex": 0,
"index": 20
},
"21: s_21": {
"variable": "s_21",
"nameRaw": "[0x40000015]",
"isGlobal": false,
"globalIndex": 0,
"index": 21
},
"22: s_22": {
"variable": "s_22",
"nameRaw": "[0x40000016]",
"isGlobal": false,
"globalIndex": 0,
"index": 22
},
"23: s_23": {
"variable": "s_23",
"nameRaw": "[0x40000017]",
"isGlobal": false,
"globalIndex": 0,
"index": 23
},
"24: s_24": {
"variable": "s_24",
"nameRaw": "[0x40000018]",
"isGlobal": false,
"globalIndex": 0,
"index": 24
},
"25: s_25": {
"variable": "s_25",
"nameRaw": "[0x00000151]",
"isGlobal": false,
"globalIndex": 0,
"index": 25
}
}
,"text records: [27]": {
"1000": [
"I need a courier, %pcf, but no common, jelly-armed, gas-headed pox of a mercenary will do. I have a letter of utmost importance to be delivered to a high dignitary who will be defended against unwelcome intrusion. In return for this, I will not only reward you with a _magicitem_, but also put in a positive word for you with the king and queen of Wayrest, but I will give you some information on the affair with Daggerfall I doubt you would receive elsewhere. Does this sound like an agreeable arrangement?"
],
"1001": [
"Dullard. Why did you let me waste my time with the likes of you?"
],
"1002": [
"Excellent. Meet me here this time tomorrow and I will give you the letter and the name and location of the recipient."
],
"1003": [
"The letter needs to be delivered, %pcf. Do not fail me in this."
],
"1004": [
"Anyway, here is the _magicitem_ I promised. Never let it be said that Prince Helseth is not a man of his bond.   Oh yes, I promised to tell you something of the situation in Daggerfall. I suspect my family has more to do with it than is commonly known. We sent advisors to urge King Lysandus and King Camaron to mend their differences on the eve of the Battle of Cryngaine Field. Lysandus was digustingly loyal to the emperor, where Camaron was fighting for more autonomy. According to the advisor's report, they arrived too late because they were waylaid by the orcs of Gortwog en route. However, I have heard stories that, at least some of our advisors arrived at Lysandus' tent and spoke to him briefly. At this time, I cannot say more. If I receive more information or if the situation progresses, I will certainly send you word."
],
"1005": [
"Lord Castellian is admitting no visitors while on holiday in __castfort_.",
"The question of succession has been distracting Lord Castellian terribly."
],
"1006": [
"Lord Castellian seems to be favoring Princess Elysana in the succession.",
"The Elder Council seems inclined to uphold the venerable law of succession."
],
"1007": [
"Lord Castellian is constantly in Prince Helseth's company since his holiday.",
"The Elder Council is talking earnestly about eliminating the law of succession."
],
"1008": [
"Yes, %pcf? Our stars seem to be rising in syndesis. What would you need?"
],
"1009": [
"I had an important assignment for you, %pcf, if you recall. Having to do with Lord Castellian? Well, now it is too late, and I am not the most patient man in Tamriel. Pray, leave me before I become brusque."
],
"1010": [
"My Dear Lord Castellian,       Sorry about the necessity of delivering this letter by the roughest possible service, but it would be unthinkable to approach you at the castle on such a delicate matter. I have long admired your loyalty to the crown and neutrality in internal affairs. Understand that I only want to save your dignity from a possibly embarrassing scenario.      The problem rests in your sister, the Lady Pasipha, who though she resides abroad still communicates regularly with members of court. I understand and respect the depth of your sibling love and affection for one another, for, in response to a curious inquiry of mine, Lady Pasipha sent me several touching letters penned in your hand.      \"Have you ever espied with delight a red berry half-drowned in cream? So I dreamed of you, my dearest love, pouring my soul into you, sweet, for your touch, dear, my soul is quite forfeit.\"      While you and I know the innocence of your fondness for the lady, the more prurient minds at court, as you are aware, are inclined toward grotesque misintepretation. Her husband, I understand, is famous for his jealous rages. I am of several minds on the matter, how to best avoid possible negative reaction, and would appreciate your response at the soonest possible opportunity. I will await you at Castle Wayrest. Helseth, Prince of Wayrest"
],
"1011": [
"Well done %pcn. Your budding reputation appears to be deserved. Lord Castellian is quite pliable now."
],
"1012": [
"It is really too bad that you were not a bit faster %pcf. My sister Elysana is betrothed. Without her opposition, it was not truly necessary to deliver that letter to Lord Castellian. However, I'm sure I can turn this to my advantage somehow."
],
"1014": [
"Why that conniving, manipulative weasel. You did well by bringing this to my attention, %pcf. Thank you."
],
"1017": [
"A page wearing the colors and pale yellow rose of Wayrest appears silently at your side. He hands you a letter and disappears as quietly as he arrived."
],
"1018": [
"A breathless courier shoves a leather pouch into your hands. A cautious examination reveals a letter and a sum of gold."
],
"1019": [
"%qdt: Prince Helseth wants me to meet him tomorrow at the Castle for the details of a quest. I will be acting as a courier."
],
"1020": [
"%qdt: Prince Helseth wants me to deliver a letter to Lord Castellian, leader of the elder council of Wayrest, in his holiday manor, _castfort_ in __castfort_. I have =1stparton_ days to deliver the letter and return."
],
"1024": [
"Prince Helseth,    I appreciate your kindness, and I will meet with you very shortly at your convenience.\" Lord Castellian"
],
"1025": [
"Lord Castellian has ordered your death. He wanted me to tell you that you know too much."
],
"1026": [
"My Dear Lord Castellian,       Forgive this rough delivery, but it would have been impolitic to approach you at the palace with this potential problem. Unfortunately, your much deserved vacation will have to temporarily suspended until this matter is settled.       I refer to your sister, Lady Pasipha. For years, she has been one of the most glamorous figures at the Wayrest court, the darling of all who appreciate beauty and grace. Rather recently, rumors have circulated that the gold she has spent on her gowns and jewels could not have possibly come from her husband, who is at present, impecunious. Distasteful conjectures followed, none of which worth the ink I would use for recitation.       To be quite blunt, a person, who must remain anonymous, postulated to me that you were borrowing funds from the royal treasury to support your sister's extravagance. Of course, I defended your honor, but copies of the Royal books were produced that seemed to support the allegation. I am thus uncertain of the best procedure to take next.       Do not doubt, sir, that I am convinced of your integrity as senior member of the Elder Circle of Wayrest. I only wish for the matter of the financial records be straightened so if they are brought to Eadwyre's attention, they can be confidently defended.       Please send a reply with this trusted courier. I would prefer to meet with you as soon as possible, of course. Very truly yours,  Helseth"
],
"1027": [
"Ah, hello again, %pcf. Here is the letter. It is to be given to Lord Castellian, the head of the elder council, who is currently at his house _castfort_ in __castfort_. I need the letter delivered and you back here in no later than =1stparton_ days -- that is essential. Like I mentioned before, Lord Castellian values his privacy to an excess. Be prepared for some resistance at your arrival in _castfort_. I would ask that you not read the letter as it is private correspondence. If word of its contents gets out, I will blame you."
],
"1028": [
"You wait while Lord Castellian reads the letter. His skin grows pale and his hand begins to shake.   \"I see. Please wait while I pen a response to Prince Helseth.\" It only takes him a minute to write the response, which he then hands you."
],
"1030": [
"This letter has been opened. You exceed the bounds of a courier, %pcn."
],
"1031": [
"So you like to read the missives of your betters. Don't expect me trust you again anytime soon."
],
"1040": [
"Dear %pcn,  Due to the recent marraige of my sister Elysana, I shall not be needing your services with regard to the delivery of the letter to Lord Castellian. Since you have acted on my behalf with honor, I have instructed the courier to give you 100 gold pieces for your time and effort so far. Helseth Prince of Wayrest"
],
"1050": [
"Lord Castellian is the most powerful of Wayrest's councilors.",
"I hear that Lord Castellian has the backing to block Prince Helseth's war plans."
]
}
}
