{
"quest info: ": {
"name": "Z0C00Y00",
"questType": "Mephala",
"membership": "NonMember",
"reputation": 0,
"delivery": "InPerson",
"childSafe": true,
"questId": 0,
"faction": "None",
"resourceId": 0,
"resourceFileName": "",
"hasDebugInfo": false
}
,"items: [1]": {
" 0: i_artifact: Artifact Artifact Ebony_Blade [1013]": {
"variable": "i_artifact",
"rewardType": "Artifact",
"category": "Artifact",
"itemId": 22,
"textRecordId1": 1013,
"textRecordId2": 0,
"index": 0,
"unknown1": "0 [0x00000000]"
}
}
,"npcs: [2]": {
" 0: n_qgfriend: Female (type Librarian)": {
"variable": "n_qgfriend",
"gender": "Female",
"facePictureIndex": 0,
"npcType": "Librarian",
"npcTypeRaw": "10 [0x000A]",
"faction": "None",
"factionRaw": "0 [0x0000]",
"textRecordId1": 1011,
"textRecordId2": 0,
"index": 0,
"null1": 0
},
" 1: n_enemy: Female (faction Boethiah) (face 1)": {
"variable": "n_enemy",
"gender": "Female",
"facePictureIndex": 1,
"npcType": "Unknown_2",
"npcTypeRaw": "65534 [0xFFFE]",
"faction": "Boethiah",
"factionRaw": "10 [0x000A]",
"textRecordId1": 0,
"textRecordId2": 0,
"index": 1,
"null1": 0
}
}
,"locations: [1]": {
" 0: l_palace: OutOfTown Palace": {
"variable": "l_palace",
"generalLocation": "OutOfTown",
"locationType": 16,
"LocationType": "Palace",
"fineLocation": 0,
"knownLocation": "None",
"doorSelector": 0,
"textRecordId1": 0,
"textRecordId2": 0,
"index": 0,
"flags": "0 [0x00]",
"objPtr": 0,
"unknown1": "65024 [0xFE00]"
}
}
,"timers: [2]": {
" 0: t_1stparton: 1.5 times travel time from here to 'l_palace' and then 'n_qgfriend'": {
"variable": "t_1stparton",
"type": "Relative4",
"typeRaw": "5 [0x05]",
"minimum": "00:00:00",
"maximum": "00:00:00",
"flags1": "1 [00000001]",
"flags2": "2 [10]",
"duration": 0,
"started": 0,
"index": 0
},
" 1: t_delay: Fixed 01:00:00": {
"variable": "t_delay",
"type": "Fixed",
"typeRaw": "1 [0x01]",
"minimum": "01:00:00",
"maximum": "00:00:00",
"flags1": "1 [00000001]",
"flags2": "0 [00]",
"duration": 0,
"started": 0,
"index": 1
}
}
,"mobs: [3]": {
" 0: m_monster: 1 Knight": {
"variable": "m_monster",
"type": "Knight",
"count": 1,
"null1": 0,
"null2": 0,
"index": 0
},
" 1: m_guards: 1 Warrior": {
"variable": "m_guards",
"type": "Warrior",
"count": 1,
"null1": 0,
"null2": 0,
"index": 1
},
" 2: m_bodyguard: 1 Giant": {
"variable": "m_bodyguard",
"type": "Giant",
"count": 1,
"null1": 0,
"null2": 0,
"index": 2
}
}
,"opCodes: [21]": {
" 0:  >> StartTimer (t_1stparton); When it expires: set s_0": {
"opCode": 12,
"argCount": 2,
"arguments:": {
"0: _": {
"type": "State",
"value": "-1",
"not": "False",
"index": "255",
"unknown1": "100680946 [0x060044F2]"
},
"1: t_1stparton": {
"type": "Timer",
"value": "0",
"not": "False",
"index": "0",
"unknown1": "14 [0x0000000E]"
}
},
"messageId": -1,
"flags": "0 [0x0000]",
"lastUpdate": 206
},
" 1:  => CreateLogEntry (1020, 0)": {
"opCode": 23,
"argCount": 3,
"arguments:": {
"0: _": {
"type": "State",
"value": "-1",
"not": "False",
"index": "255",
"unknown1": "100680946 [0x060044F2]"
},
"1: 1020": {
"type": "Value",
"value": "1020",
"not": "False",
"index": "0",
"unknown1": "14 [0x0000000E]"
},
"2: 0": {
"type": "Value",
"value": "0",
"not": "False",
"index": "0",
"unknown1": "1156761600 [0x44F2C800]"
}
},
"messageId": -1,
"flags": "0 [0x0000]",
"lastUpdate": 206
},
" 2:  => PlaceNpcAt (n_enemy, l_palace)": {
"opCode": 30,
"argCount": 3,
"arguments:": {
"0: _": {
"type": "State",
"value": "-1",
"not": "False",
"index": "255",
"unknown1": "100680946 [0x060044F2]"
},
"1: n_enemy": {
"type": "Npc",
"value": "1",
"not": "False",
"index": "1",
"unknown1": "14 [0x0000000E]"
},
"2: l_palace": {
"type": "Location",
"value": "0",
"not": "False",
"index": "0",
"unknown1": "1156761600 [0x44F2C800]"
}
},
"messageId": -1,
"flags": "0 [0x0000]",
"lastUpdate": 206
},
" 3:  >> WhenAtLocation (l_palace): set s_6": {
"opCode": 43,
"argCount": 3,
"arguments:": {
"0: _": {
"type": "State",
"value": "-1",
"not": "False",
"index": "255",
"unknown1": "100680946 [0x060044F2]"
},
"1: s_6": {
"type": "State",
"value": "6",
"not": "False",
"index": "6",
"unknown1": "14 [0x0000000E]"
},
"2: l_palace": {
"type": "Location",
"value": "0",
"not": "False",
"index": "0",
"unknown1": "1156761600 [0x44F2C800]"
}
},
"messageId": -1,
"flags": "0 [0x0000]",
"lastUpdate": 206
},
" 4: s_6 => HideNpc (n_enemy)": {
"opCode": 46,
"argCount": 2,
"arguments:": {
"0: s_6": {
"type": "State",
"value": "6",
"not": "False",
"index": "6",
"unknown1": "100680946 [0x060044F2]"
},
"1: n_enemy": {
"type": "Npc",
"value": "1",
"not": "False",
"index": "1",
"unknown1": "14 [0x0000000E]"
}
},
"messageId": -1,
"flags": "0 [0x0000]",
"lastUpdate": 206
},
" 5: s_6 => PlaceMobAtLocation (m_monster, l_palace)": {
"opCode": 22,
"argCount": 3,
"arguments:": {
"0: s_6": {
"type": "State",
"value": "6",
"not": "False",
"index": "6",
"unknown1": "100680946 [0x060044F2]"
},
"1: m_monster": {
"type": "Mob",
"value": "0",
"not": "False",
"index": "0",
"unknown1": "14 [0x0000000E]"
},
"2: l_palace": {
"type": "Location",
"value": "0",
"not": "False",
"index": "0",
"unknown1": "1156761600 [0x44F2C800]"
}
},
"messageId": -1,
"flags": "0 [0x0000]",
"lastUpdate": 206
},
" 6: s_6 => CreateFoe(m_guards, 2, 25%, 25)": {
"opCode": 9,
"argCount": 5,
"arguments:": {
"0: s_6": {
"type": "State",
"value": "6",
"not": "False",
"index": "6",
"unknown1": "100680946 [0x060044F2]"
},
"1: m_guards": {
"type": "Mob",
"value": "1",
"not": "False",
"index": "1",
"unknown1": "14 [0x0000000E]"
},
"2: 2": {
"type": "Value",
"value": "2",
"not": "False",
"index": "0",
"unknown1": "1156761600 [0x44F2C800]"
},
"3: 25": {
"type": "Value",
"value": "25",
"not": "False",
"index": "0",
"unknown1": "1997668352 [0x77120000]"
},
"4: 10": {
"type": "Value",
"value": "10",
"not": "False",
"index": "0",
"unknown1": "17825792 [0x01100000]"
}
},
"messageId": -1,
"flags": "0 [0x0000]",
"lastUpdate": 206
},
" 7:  >> IfMobHurtByPlayer (m_guards): set s_9 [Msg 1040]": {
"opCode": 21,
"argCount": 2,
"arguments:": {
"0: s_9": {
"type": "State",
"value": "9",
"not": "False",
"index": "9",
"unknown1": "100680946 [0x060044F2]"
},
"1: m_guards": {
"type": "Mob",
"value": "1",
"not": "False",
"index": "1",
"unknown1": "14 [0x0000000E]"
}
},
"messageId": 1040,
"flags": "0 [0x0000]",
"lastUpdate": 206
},
" 8:  >> IfMobHurtByPlayer (m_monster): set s_7": {
"opCode": 21,
"argCount": 2,
"arguments:": {
"0: s_7": {
"type": "State",
"value": "7",
"not": "False",
"index": "7",
"unknown1": "100680946 [0x060044F2]"
},
"1: m_monster": {
"type": "Mob",
"value": "0",
"not": "False",
"index": "0",
"unknown1": "14 [0x0000000E]"
}
},
"messageId": -1,
"flags": "0 [0x0000]",
"lastUpdate": 206
},
" 9: s_7 => Say (1041)": {
"opCode": 51,
"argCount": 1,
"arguments:": {
"0: s_7": {
"type": "State",
"value": "7",
"not": "False",
"index": "7",
"unknown1": "100680946 [0x060044F2]"
}
},
"messageId": 1041,
"flags": "0 [0x0000]",
"lastUpdate": 206
},
"10: s_7 => CreateFoe(m_bodyguard, 1, 100%, 100)": {
"opCode": 9,
"argCount": 5,
"arguments:": {
"0: s_7": {
"type": "State",
"value": "7",
"not": "False",
"index": "7",
"unknown1": "100680946 [0x060044F2]"
},
"1: m_bodyguard": {
"type": "Mob",
"value": "2",
"not": "False",
"index": "2",
"unknown1": "14 [0x0000000E]"
},
"2: 1": {
"type": "Value",
"value": "1",
"not": "False",
"index": "0",
"unknown1": "1156761600 [0x44F2C800]"
},
"3: 100": {
"type": "Value",
"value": "100",
"not": "False",
"index": "0",
"unknown1": "1997668352 [0x77120000]"
},
"4: 1": {
"type": "Value",
"value": "1",
"not": "False",
"index": "0",
"unknown1": "17825792 [0x01100000]"
}
},
"messageId": -1,
"flags": "0 [0x0000]",
"lastUpdate": 206
},
"11:  >> IfMobsKilled (m_monster, 1): set s_3": {
"opCode": 2,
"argCount": 3,
"arguments:": {
"0: s_3": {
"type": "State",
"value": "3",
"not": "False",
"index": "3",
"unknown1": "100680946 [0x060044F2]"
},
"1: m_monster": {
"type": "Mob",
"value": "0",
"not": "False",
"index": "0",
"unknown1": "14 [0x0000000E]"
},
"2: 1": {
"type": "Value",
"value": "1",
"not": "False",
"index": "0",
"unknown1": "1156761600 [0x44F2C800]"
}
},
"messageId": -1,
"flags": "0 [0x0000]",
"lastUpdate": 206
},
"12: s_3 => Say (1030)": {
"opCode": 51,
"argCount": 1,
"arguments:": {
"0: s_3": {
"type": "State",
"value": "3",
"not": "False",
"index": "3",
"unknown1": "100680946 [0x060044F2]"
}
},
"messageId": 1030,
"flags": "0 [0x0000]",
"lastUpdate": 206
},
"13:  >> IfNpcClicked (n_qgfriend): set s_4": {
"opCode": 28,
"argCount": 2,
"arguments:": {
"0: s_4": {
"type": "State",
"value": "4",
"not": "False",
"index": "4",
"unknown1": "100680946 [0x060044F2]"
},
"1: n_qgfriend": {
"type": "Npc",
"value": "0",
"not": "False",
"index": "0",
"unknown1": "14 [0x0000000E]"
}
},
"messageId": -1,
"flags": "0 [0x0000]",
"lastUpdate": 206
},
"14:  >> If (s_4 and s_3): set s_2": {
"opCode": 52,
"argCount": 5,
"arguments:": {
"0: s_2": {
"type": "State",
"value": "2",
"not": "False",
"index": "2",
"unknown1": "100680946 [0x060044F2]"
},
"1: s_4": {
"type": "State",
"value": "4",
"not": "False",
"index": "4",
"unknown1": "14 [0x0000000E]"
},
"2: s_3": {
"type": "State",
"value": "3",
"not": "False",
"index": "3",
"unknown1": "1156761600 [0x44F2C800]"
},
"3: ": {
"type": "State",
"value": "-2",
"not": "False",
"index": "254",
"unknown1": "1997668352 [0x77120000]"
},
"4: ": {
"type": "State",
"value": "-2",
"not": "False",
"index": "254",
"unknown1": "17825792 [0x01100000]"
}
},
"messageId": -1,
"flags": "0 [0x0000]",
"lastUpdate": 206
},
"15:  >> If (s_4 and not s_3): set s_5": {
"opCode": 52,
"argCount": 5,
"arguments:": {
"0: s_5": {
"type": "State",
"value": "5",
"not": "False",
"index": "5",
"unknown1": "100680946 [0x060044F2]"
},
"1: s_4": {
"type": "State",
"value": "4",
"not": "False",
"index": "4",
"unknown1": "14 [0x0000000E]"
},
"2: not s_3": {
"type": "State",
"value": "3",
"not": "True",
"index": "3",
"unknown1": "1156761600 [0x44F2C800]"
},
"3: ": {
"type": "State",
"value": "-2",
"not": "False",
"index": "254",
"unknown1": "1997668352 [0x77120000]"
},
"4: ": {
"type": "State",
"value": "-2",
"not": "False",
"index": "254",
"unknown1": "17825792 [0x01100000]"
}
},
"messageId": -1,
"flags": "0 [0x0000]",
"lastUpdate": 206
},
"16: s_5 => Unset (s_4, s_5)": {
"opCode": 7,
"argCount": 5,
"arguments:": {
"0: s_5": {
"type": "State",
"value": "5",
"not": "False",
"index": "5",
"unknown1": "100680946 [0x060044F2]"
},
"1: s_4": {
"type": "State",
"value": "4",
"not": "False",
"index": "4",
"unknown1": "14 [0x0000000E]"
},
"2: s_5": {
"type": "State",
"value": "5",
"not": "False",
"index": "5",
"unknown1": "1156761600 [0x44F2C800]"
},
"3: ": {
"type": "State",
"value": "-2",
"not": "False",
"index": "254",
"unknown1": "1997668352 [0x77120000]"
},
"4: ": {
"type": "State",
"value": "-2",
"not": "False",
"index": "254",
"unknown1": "17825792 [0x01100000]"
}
},
"messageId": -1,
"flags": "0 [0x0000]",
"lastUpdate": 206
},
"17: s_2 => QuestSuccess (i_artifact)": {
"opCode": 4,
"argCount": 5,
"arguments:": {
"0: s_2": {
"type": "State",
"value": "2",
"not": "False",
"index": "2",
"unknown1": "100680946 [0x060044F2]"
},
"1: i_artifact": {
"type": "Item",
"value": "0",
"not": "False",
"index": "0",
"unknown1": "14 [0x0000000E]"
},
"2: ": {
"type": "Item",
"value": "-1",
"not": "False",
"index": "255",
"unknown1": "1156761600 [0x44F2C800]"
},
"3: ": {
"type": "Item",
"value": "-1",
"not": "False",
"index": "255",
"unknown1": "1997668352 [0x77120000]"
},
"4: ": {
"type": "Item",
"value": "-1",
"not": "False",
"index": "255",
"unknown1": "17825792 [0x01100000]"
}
},
"messageId": -1,
"flags": "0 [0x0000]",
"lastUpdate": 206
},
"18: s_2 >> StartTimer (t_delay); When it expires: set s_8": {
"opCode": 12,
"argCount": 2,
"arguments:": {
"0: s_2": {
"type": "State",
"value": "2",
"not": "False",
"index": "2",
"unknown1": "100680946 [0x060044F2]"
},
"1: t_delay": {
"type": "Timer",
"value": "1",
"not": "False",
"index": "1",
"unknown1": "14 [0x0000000E]"
}
},
"messageId": -1,
"flags": "0 [0x0000]",
"lastUpdate": 206
},
"19: s_8 => EndQuest ()": {
"opCode": 6,
"argCount": 1,
"arguments:": {
"0: s_8": {
"type": "State",
"value": "8",
"not": "False",
"index": "8",
"unknown1": "100680946 [0x060044F2]"
}
},
"messageId": -1,
"flags": "0 [0x0000]",
"lastUpdate": 206
},
"20: s_0 => EndQuest ()": {
"opCode": 6,
"argCount": 1,
"arguments:": {
"0: s_0": {
"type": "State",
"value": "0",
"not": "False",
"index": "0",
"unknown1": "100680946 [0x060044F2]"
}
},
"messageId": -1,
"flags": "0 [0x0000]",
"lastUpdate": 206
}
}
,"states: [10]": {
" 0: s_1stparton": {
"variable": "s_1stparton",
"isGlobal": false,
"globalIndex": 0,
"index": 0
},
" 1: s_2ndparton": {
"variable": "s_2ndparton",
"isGlobal": false,
"globalIndex": 0,
"index": 1
},
" 2: s_pcgetsgold": {
"variable": "s_pcgetsgold",
"isGlobal": false,
"globalIndex": 0,
"index": 2
},
" 3: s_mondead": {
"variable": "s_mondead",
"isGlobal": false,
"globalIndex": 0,
"index": 3
},
" 4: s_npcclicked": {
"variable": "s_npcclicked",
"isGlobal": false,
"globalIndex": 0,
"index": 4
},
" 5: s_clearclick": {
"variable": "s_clearclick",
"isGlobal": false,
"globalIndex": 0,
"index": 5
},
" 6: s_0000679f": {
"variable": "s_0000679f",
"isGlobal": false,
"globalIndex": 0,
"index": 6
},
" 7: s_00006967": {
"variable": "s_00006967",
"isGlobal": false,
"globalIndex": 0,
"index": 7
},
" 8: s_delay": {
"variable": "s_delay",
"isGlobal": false,
"globalIndex": 0,
"index": 8
},
" 9: s_hitguard": {
"variable": "s_hitguard",
"isGlobal": false,
"globalIndex": 0,
"index": 9
}
}
,"text records: [18]": {
"1000": [
"I might have known it would be you. I ought  to never answer these summonings. Well, perhaps  it is natural for a worm to want to evolve  into a wasp. Very well, %pcf, I will  give you power, but you must do something for  me first. I need someone to assassinate a  certain troublesome minor noble. Can I rely  on you for that?"
],
"1001": [
"That is just as well. I have better uses  for my time than building a power base  for ungrateful, lazy guttersnipes."
],
"1002": [
"Well, that's something, anyhow. You can find  this irksome official _enemy_  in __palace_, snug and secure in his palace,  as he believes. I don't know how you're  going to gain entry, but perhaps you will come  up with an idea. Perhaps. If you don't manage  to kill yourself, go to ___qgfriend_  and I'll arrange for a servant to bring you  your new power source, the _artifact_. I  will ask my servant _qgfriend_ to  wait for you for =1stparton_ days at __qgfriend_.  Do not, please, be late. That is all."
],
"1003": [
"No, no, no, no! You kill the  knight in __palace_  first, then you come to see me!  %oth, Mephala was right."
],
"1004": [
"Good day, %pcf, I'm _qgfriend_.",
"Mephala told me that you might show up, but she  did cast some doubts about the chances of you  surviving the encounter with _enemy_.  Well, it's a good thing I brought the Blade, then,  isn't it? Sorry if you got a bad talking to  from Mephala. With _enemy_  dead, she should be in a lot better mood.  And for that alone, I thank you."
],
"1005": [
"_enemy_ says %g can find %g3 way to the headquarters of the Dark Brotherhood.",
"The Dark Brotherhood must be terrified with _enemy_ working against them."
],
"1006": [
"The Dark Brotherhood sent someone to get _enemy_, but they couldn't kill %g2!",
"After that failed assassination attempt, _enemy_ has moved out of __palace_."
],
"1007": [
"_enemy_ must have been too close to finding the location of Nightside Asylum.",
"I guess the Dark Brotherhood heard about _enemy_ and %g3 ambitions."
],
"1008": [
"."
],
"1009": [
"."
],
"1011": [
"_qgfriend_ is that snobby =qgfriend_ slumming in __qgfriend_, %di of here.",
"_qgfriend_ is the name of that =qgfriend_ %di of here in __qgfriend_."
],
"1012": [
"_qgfriend_ is one of Mephala's agents in %reg, operating out of __qgfriend_.",
"_qgfriend_ is a pawn of Mephala; %g's a =qgfriend_ at __qgfriend_."
],
"1013": [
"Mephala is the Daedra Regent of Murder and Patroness of the Dark Brotherhood.",
"Mephala is one of the Princes of Oblivion whose sphere is Murder."
],
"1014": [
"The _artifact_ is an artifact of vampiric power, draining its victim  of life, even as it feeds its owner."
],
"1020": [
"%qdt: I have made a contract with one of the Daedra Princes, Mephala -- I will slay an official named _enemy_ and she will give me an artifact called the _artifact_. Her contact _qgfriend_ will wait for me for =1stparton_ days in __qgfriend_ of ___qgfriend_. The only other complication is that Mephala tells me that _enemy_ lives in the palace at __palace_. Could be difficult to get to %g2."
],
"1030": [
"Mephala would be proud--  _enemy_ is dead.  Time  to make your escape."
],
"1040": [
"Who are you and what are you doing in here?"
],
"1041": [
"You sneaking assassins are all the same.  That's  why I decided to get myself some real protection.  =bodyguard_!  Wake up, you big oaf.  Kill!"
]
}
}
